Workbook

Sheet Explanatory notes
B39: 2001-2018 | C39: 2019 onwards
A40: Anyone who filed an IR3 personal tax return for that income year, even if they filed a nil return or a loss | B40: Included | C40: Included
A41: Anyone who received a personal tax summary(PTS) for that income year. PTSs were only automatically issued for certain people who had not filed an IR3. Others could request to have one. | B41: Included | C41: N/A
A42: Anyone who paid PAYE via an employer, including recipients of wages and salaries, taxable welfare benefits, New Zealand Superannuation, earnings-related accident compensation income, student allowances, and paid parental leave, even if they did not file a return. | B42: Included | C42: Included
A43: Anyone who received an automatic income tax assessment at year end. From 2019, these are created for anybody with income during the year from any source for which Inland Revenue holds information; for example wages and salaries, taxable welfare benefits, New Zealand Superannuation, earnings-related accident compensation income, student allowances, and paid parental leave interest, dividends, and income earned through portfolio investment entities (PIEs) if it was taxed at the wrong rate | B43: N/A | C43: Included
A44: Individuals with part year income. | B44: Included if they filed or had PAYE income | C44: Included if they filed or had automatic assessment income
A45: Individuals whose only income was from interest or dividends, all fully taxed at source so they did not, prior to 2019, need to file a tax return | B45: Excluded | C45: Included. Over time, coverage has improved by having both IRD numbers for joint bank accounts.
A46: Individuals with no taxable income and who did not file a tax return | B46: Excluded | C46: Excluded
A47: Individuals who filed a non-resident return | B47: Excluded unless picked up in PAYE | C47: Excluded
A48: Individuals whose only income was from PIE(s), all fully and correctly taxed at source | B48: Excluded | C48: Excluded
A49: Children | B49: Included if they filed a tax return or had PAYE income such as a wage or salary | C49: Included if they filed or had automatic assessment income
B57: 2001-2018 | C57: 2019 onwards
A58: PAYE earnings such as wages and salaries, taxable welfare benefits, New Zealand Superannuation, earnings-related accident compensation income, student allowances, schedular payments, and paid parental leave. | B58: Included | C58: Included
A59: Income sources specifically returned on the IR3 form such as self employment, shareholder salaries, estate or trust income, overseas income, partnership income, look through company income, Maori authority distributions, rental income (including bright line property income), income from taxable sale/disposal of property, Government subsidy and any other taxable income | B59: Included if IR3 filed | C59: Included if IR3 filed
A60: Deductions such as brought forward losses, LAQC or look through losses received from companies, partnership losses, deductible expenses such as return preparation fees or schedular expenses | B60: Included if IR3 filed | C60: Included if IR3 filed
A61: Interest and dividends | B61: Included only if IR3 filed or income disclosed for personal tax summary | C61: Included for all
A62: PIE income (for example KiwiSaver earnings) | B62: Excluded | C62: Excluded

Sheet Income distribution graphs
P65: .

Sheet Income tables 2001-24
A2: Income from indivduals from 2001 to 2024
B4: 2001 | E4: 2002 | H4: 2003 | K4: 2004 | N4: 2005 | Q4: 2006 | T4: 2007 | W4: 2008 | Z4: 2009 | AD4: 2010 | AG4: 2011 | AJ4: 2012 | AM4: 2013 | AP4: 2014 | AS4: 2015 | AV4: 2016 | AY4: 2017 | BB4: 2018 | BF4: 2019 | BI4: 2020 | BL4: 2021 | BO4: 2022 | BR4: 2023 | BU4: 2024
A5: Taxable Income | B5: Number of People | C5: Taxable Income ($M) | D5: Tax on Taxable Income ($M) | E5: Number of People | F5: Taxable Income ($M) | G5: Tax on Taxable Income ($M) | H5: Number of People | I5: Taxable Income ($M) | J5: Tax on Taxable Income ($M) | K5: Number of People | L5: Taxable Income ($M) | M5: Tax on Taxable Income ($M) | N5: Number of People | O5: Taxable Income ($M) | P5: Tax on Taxable Income ($M) | Q5: Number of People | R5: Taxable Income ($M) | S5: Tax on Taxable Income ($M) | T5: Number of People | U5: Taxable Income ($M) | V5: Tax on Taxable Income ($M) | W5: Number of People | X5: Taxable Income ($M) | Y5: Tax on Taxable Income ($M) | Z5: Number of People | AA5: Taxable Income ($M) | AB5: Tax on Taxable Income ($M) | AC5: Taxable Income | AD5: Number of People | AE5: Taxable Income ($M) | AF5: Tax on Taxable Income ($M) | AG5: Number of People | AH5: Taxable Income ($M) | AI5: Tax on Taxable Income ($M) | AJ5: Number of People | AK5: Taxable Income ($M) | AL5: Tax on Taxable Income ($M) | AM5: Number of People | AN5: Taxable Income ($M) | AO5: Tax on Taxable Income ($M) | AP5: Number of People | AQ5: Taxable Income ($M) | AR5: Tax on Taxable Income ($M) | AS5: Number of People | AT5: Taxable Income ($M) | AU5: Tax on Taxable Income ($M) | AV5: Number of People | AW5: Taxable Income ($M) | AX5: Tax on Taxable Income ($M) | AY5: Number of People | AZ5: Taxable Income ($M) | BA5: Tax on Taxable Income ($M) | BB5: Number of People | BC5: Taxable Income ($M) | BD5: Tax on Taxable Income ($M) | BE5: Taxable Income | BF5: Number of People | BG5: Taxable Income ($M) | BH5: Tax on Taxable Income ($M) | BI5: Number of People | BJ5: Taxable Income ($M) | BK5: Tax on Taxable Income ($M) | BL5: Number of People | BM5: Taxable Income ($M) | BN5: Tax on Taxable Income ($M) | BO5: Number of People | BP5: Taxable Income ($M) | BQ5: Tax on Taxable Income ($M) | BR5: Number of People | BS5: Taxable Income ($M) | BT5: Tax on Taxable Income ($M) | BU5: Number of People | BV5: Taxable Income ($M) | BW5: Tax on Taxable Income ($M)
AC6: bands to $300,000 | BE6: bands to $1,000,000
BE8: nil | BF8: 76580 | BG8: 0 | BH8: -0.03564592 | BI8: 92610 | BJ8: 0 | BK8: -0.0949011 | BL8: 70050 | BM8: 0 | BN8: -0.0876497 | BO8: 55850 | BP8: 0 | BQ8: -0.08479783 | BR8: 56510 | BS8: 0 | BT8: -0.06978791 | BU8: 54800 | BV8: 0 | BW8: -0.06315365
A9: nil | B9: 107720 | C9: 0 | D9: 0 | E9: 113900 | F9: 0 | G9: 0 | H9: 117580 | I9: 0 | J9: 0 | K9: 121650 | L9: 0 | M9: 0 | N9: 126520 | O9: 0 | P9: 0 | Q9: 141660 | R9: 0 | S9: 0 | T9: 117240 | U9: 0 | V9: 0 | W9: 129740 | X9: 0 | Y9: 0 | Z9: 136150 | AA9: 0 | AB9: 0 | AC9: nil | AD9: 134610 | AE9: 0 | AF9: 0 | AG9: 126530 | AH9: 0 | AI9: 0 | AJ9: 113870 | AK9: 0 | AL9: 0 | AM9: 107470 | AN9: 0 | AO9: 0 | AP9: 104350 | AQ9: 0 | AR9: 0 | AS9: 102070 | AT9: 0 | AU9: 0 | AV9: 109120 | AW9: 0 | AX9: 0 | AY9: 102220 | AZ9: 0 | BA9: 0 | BB9: 94210 | BC9: 0 | BD9: 0 | BE9: $0.01 - $100 | BF9: 309730 | BG9: 3.49 | BH9: 0.36685982 | BI9: 308450 | BJ9: 3.5 | BK9: 0.3635929 | BL9: 347310 | BM9: 3 | BN9: 0.3110261 | BO9: 349990 | BP9: 3.19 | BQ9: 0.33390914 | BR9: 349080 | BS9: 5.1 | BT9: 0.53486419 | BU9: 331010 | BV9: 5.46 | BW9: 0.57264757
A10: $1 - $1,000 | B10: 102510 | C10: 45.160237 | D10: 6.3934705 | E10: 105820 | F10: 47.869558 | G10: 6.1796478 | H10: 107160 | I10: 49.6 | J10: 6.5 | K10: 101730 | L10: 46.9 | M10: 6.2 | N10: 109680 | O10: 49.9 | P10: 6.7 | Q10: 107530 | R10: 50.5 | S10: 6.7 | T10: 106050 | U10: 50.3 | V10: 6.4 | W10: 98580 | X10: 46.4 | Y10: 5.9 | Z10: 93160 | AA10: 44.9 | AB10: 5.1 | AC10: $101 - $1,000 | AD10: 91280 | AE10: 44.9 | AF10: 4.7 | AG10: 83230 | AH10: 41.3 | AI10: 3.9 | AJ10: 83000 | AK10: 40.4 | AL10: 3.5 | AM10: 81400 | AN10: 40.3 | AO10: 4.2 | AP10: 83060 | AQ10: 39.7 | AR10: 4.2 | AS10: 86290 | AT10: 41.7 | AU10: 4.4 | AV10: 79110 | AW10: 38.3 | AX10: 4 | AY10: 77220 | AZ10: 37.9 | BA10: 4 | BB10: 80880 | BC10: 36.9 | BD10: 3.9 | BE10: $101 - $1,000 | BF10: 102990 | BG10: 47.75 | BH10: 5.013631 | BI10: 102610 | BJ10: 47.2 | BK10: 4.9512401 | BL10: 81270 | BM10: 38.5 | BN10: 4.0372742 | BO10: 75040 | BP10: 34.73 | BQ10: 3.6437349 | BR10: 112490 | BS10: 47.12 | BT10: 4.9453852 | BU10: 136970 | BV10: 55.76 | BW10: 5.8526859
A11: $1,001 - $2,000 | B11: 68850 | C11: 101.85903 | D11: 14.966178 | E11: 69870 | F11: 103.30362 | G11: 13.797671 | H11: 70000 | I11: 103.5 | J11: 14 | K11: 69610 | L11: 103.4 | M11: 13.9 | N11: 69510 | O11: 103 | P11: 14.1 | Q11: 74370 | R11: 111.2 | S11: 15 | T11: 72060 | U11: 106.7 | V11: 13.5 | W11: 66330 | X11: 99.5 | Y11: 12.2 | Z11: 64330 | AA11: 95.5 | AB11: 10.7 | AC11: $1,001 - $2,000 | AD11: 61820 | AE11: 92 | AF11: 9.7 | AG11: 59530 | AH11: 88.8 | AI11: 8.4 | AJ11: 56010 | AK11: 83.1 | AL11: 7.3 | AM11: 55590 | AN11: 82.8 | AO11: 8.7 | AP11: 58080 | AQ11: 86.5 | AR11: 9.1 | AS11: 52960 | AT11: 79.2 | AU11: 8.3 | AV11: 53730 | AW11: 79.6 | AX11: 8.3 | AY11: 52250 | AZ11: 77.6 | BA11: 8.1 | BB11: 52210 | BC11: 77.5 | BD11: 8.1 | BE11: $1,001 - $2,000 | BF11: 57430 | BG11: 84.5 | BH11: 8.8711287 | BI11: 55250 | BJ11: 81.1 | BK11: 8.5106639 | BL11: 43890 | BM11: 64.1 | BN11: 6.7293922 | BO11: 41470 | BP11: 60.07 | BQ11: 6.3060877 | BR11: 49700 | BS11: 72.19 | BT11: 7.5764595 | BU11: 53720 | BV11: 77.71 | BW11: 8.1575698
A12: $2,001 - $3,000 | B12: 57490 | C12: 143.66619 | D12: 22.12776 | E12: 59780 | F12: 149.87496 | G12: 21.094348 | H12: 60420 | I12: 149.7 | J12: 21.1 | K12: 60660 | L12: 150.9 | M12: 21.2 | N12: 59970 | O12: 148.8 | P12: 21 | Q12: 59960 | R12: 150.1 | S12: 21.1 | T12: 60320 | U12: 150 | V12: 19.1 | W12: 59780 | X12: 149.1 | Y12: 18 | Z12: 57670 | AA12: 143.8 | AB12: 16.2 | AC12: $2,001 - $3,000 | AD12: 54910 | AE12: 137.7 | AF12: 14.4 | AG12: 54910 | AH12: 136.3 | AI12: 13.2 | AJ12: 51330 | AK12: 128 | AL12: 11.5 | AM12: 44070 | AN12: 109.8 | AO12: 11.5 | AP12: 46360 | AQ12: 115.7 | AR12: 12.1 | AS12: 46240 | AT12: 115.8 | AU12: 12.1 | AV12: 46470 | AW12: 116 | AX12: 12.1 | AY12: 45470 | AZ12: 113.4 | BA12: 11.9 | BB12: 44700 | BC12: 111.7 | BD12: 11.7 | BE12: $2,001 - $3,000 | BF12: 45960 | BG12: 114.57 | BH12: 12.028462 | BI12: 43690 | BJ12: 108.9 | BK12: 11.433214 | BL12: 33430 | BM12: 83.1 | BN12: 8.7279939 | BO12: 31820 | BP12: 78.98 | BQ12: 8.2903635 | BR12: 37290 | BS12: 92.73 | BT12: 9.7348547 | BU12: 38310 | BV12: 95 | BW12: 9.9725451
A13: $3,001 - $4,000 | B13: 52640 | C13: 184.33413 | D13: 28.515442 | E13: 53650 | F13: 187.80132 | G13: 26.691089 | H13: 53060 | I13: 185.5 | J13: 26.5 | K13: 55380 | L13: 193.9 | M13: 27.5 | N13: 55960 | O13: 195.1 | P13: 28.1 | Q13: 53200 | R13: 186 | S13: 26.5 | T13: 55110 | U13: 192.8 | V13: 25.9 | W13: 53130 | X13: 185.7 | Y13: 23.9 | Z13: 51490 | AA13: 179.6 | AB13: 21.5 | AC13: $3,001 - $4,000 | AD13: 47800 | AE13: 167 | AF13: 18.3 | AG13: 46550 | AH13: 162.4 | AI13: 16.5 | AJ13: 43440 | AK13: 151.6 | AL13: 14 | AM13: 44770 | AN13: 156.6 | AO13: 16.4 | AP13: 42390 | AQ13: 148.4 | AR13: 15.6 | AS13: 45950 | AT13: 160.5 | AU13: 16.8 | AV13: 42760 | AW13: 149.6 | AX13: 15.6 | AY13: 41930 | AZ13: 146.5 | BA13: 15.3 | BB13: 41580 | BC13: 145.3 | BD13: 15.3 | BE13: $3,001 - $4,000 | BF13: 41970 | BG13: 146.78 | BH13: 15.408357 | BI13: 40070 | BJ13: 140.1 | BK13: 14.708419 | BL13: 29990 | BM13: 104.9 | BN13: 11.011316 | BO13: 28280 | BP13: 98.87 | BQ13: 10.377414 | BR13: 31960 | BS13: 111.58 | BT13: 11.714206 | BU13: 33200 | BV13: 115.89 | BW13: 12.165652
A14: $4,001 - $5,000 | B14: 55290 | C14: 249.72585 | D14: 38.966654 | E14: 53540 | F14: 240.3503 | G14: 34.445102 | H14: 49660 | I14: 223.9 | J14: 32.3 | K14: 52620 | L14: 236.6 | M14: 34.2 | N14: 53320 | O14: 239.9 | P14: 34.4 | Q14: 51640 | R14: 233.4 | S14: 33.6 | T14: 50710 | U14: 228.1 | V14: 31.4 | W14: 52330 | X14: 235.5 | Y14: 31.6 | Z14: 48490 | AA14: 218.1 | AB14: 27 | AC14: $4,001 - $5,000 | AD14: 47940 | AE14: 216.7 | AF14: 24.5 | AG14: 45080 | AH14: 203.1 | AI14: 21.3 | AJ14: 43150 | AK14: 194.1 | AL14: 18.4 | AM14: 40720 | AN14: 183.3 | AO14: 19.2 | AP14: 39930 | AQ14: 179.9 | AR14: 18.9 | AS14: 43770 | AT14: 197 | AU14: 20.7 | AV14: 39990 | AW14: 180.2 | AX14: 18.8 | AY14: 39370 | AZ14: 177.3 | BA14: 18.5 | BB14: 39370 | BC14: 177.1 | BD14: 18.6 | BE14: $4,001 - $5,000 | BF14: 39490 | BG14: 177.66 | BH14: 18.652454 | BI14: 37680 | BJ14: 169.5 | BK14: 17.795621 | BL14: 28970 | BM14: 130.3 | BN14: 13.682033 | BO14: 26770 | BP14: 120.41 | BQ14: 12.639099 | BR14: 30670 | BS14: 137.96 | BT14: 14.484135 | BU14: 30890 | BV14: 138.84 | BW14: 14.575737
A15: $5,001 - $6,000 | B15: 49590 | C15: 273.07922 | D15: 42.727397 | E15: 55240 | F15: 302.61513 | G15: 43.680848 | H15: 48800 | I15: 269.2 | J15: 39 | K15: 50480 | L15: 277.4 | M15: 40.2 | N15: 50330 | O15: 276.3 | P15: 40.2 | Q15: 51870 | R15: 285 | S15: 41.6 | T15: 49970 | U15: 274.5 | V15: 39 | W15: 48080 | X15: 263.8 | Y15: 36.6 | Z15: 47450 | AA15: 261 | AB15: 33.1 | AC15: $5,001 - $6,000 | AD15: 49890 | AE15: 274.7 | AF15: 31.7 | AG15: 43100 | AH15: 237.5 | AI15: 24.9 | AJ15: 42090 | AK15: 231.3 | AL15: 22.3 | AM15: 42550 | AN15: 234 | AO15: 24.5 | AP15: 42470 | AQ15: 233.7 | AR15: 24.5 | AS15: 42170 | AT15: 232.3 | AU15: 24.4 | AV15: 40070 | AW15: 220.5 | AX15: 23.1 | AY15: 39780 | AZ15: 218.8 | BA15: 22.9 | BB15: 38750 | BC15: 213.1 | BD15: 22.4 | BE15: $5,001 - $6,000 | BF15: 38620 | BG15: 212.35 | BH15: 22.293127 | BI15: 36180 | BJ15: 199 | BK15: 20.890539 | BL15: 27250 | BM15: 150 | BN15: 15.742491 | BO15: 25980 | BP15: 142.86 | BQ15: 14.997924 | BR15: 29310 | BS15: 161.08 | BT15: 16.910683 | BU15: 29510 | BV15: 162.21 | BW15: 17.029922
A16: $6,001 - $7,000 | B16: 57110 | C16: 370.888 | D16: 59.00967 | E16: 50990 | F16: 331.8031 | G16: 48.616557 | H16: 51510 | I16: 334.7 | J16: 48.9 | K16: 48990 | L16: 318.4 | M16: 46.7 | N16: 48840 | O16: 317.4 | P16: 46.6 | Q16: 50020 | R16: 324.7 | S16: 47.7 | T16: 52470 | U16: 341.2 | V16: 48.9 | W16: 49720 | X16: 324.3 | Y16: 46.1 | Z16: 49760 | AA16: 323.7 | AB16: 41.2 | AC16: $6,001 - $7,000 | AD16: 43190 | AE16: 280.5 | AF16: 32.7 | AG16: 46050 | AH16: 299.4 | AI16: 32.2 | AJ16: 42800 | AK16: 278.7 | AL16: 27.4 | AM16: 42290 | AN16: 274.9 | AO16: 28.8 | AP16: 42340 | AQ16: 275.4 | AR16: 28.9 | AS16: 40980 | AT16: 266.5 | AU16: 28 | AV16: 39590 | AW16: 257.2 | AX16: 26.9 | AY16: 38960 | AZ16: 253.3 | BA16: 26.5 | BB16: 38240 | BC16: 248.5 | BD16: 26.1 | BE16: $6,001 - $7,000 | BF16: 37150 | BG16: 241.49 | BH16: 25.354785 | BI16: 35560 | BJ16: 231.3 | BK16: 24.280207 | BL16: 27420 | BM16: 178.3 | BN16: 18.713498 | BO16: 25180 | BP16: 163.57 | BQ16: 17.172279 | BR16: 28580 | BS16: 185.82 | BT16: 19.50658 | BU16: 28180 | BV16: 183.06 | BW16: 19.219654
A17: $7,001 - $8,000 | B17: 76280 | C17: 574.54051 | D17: 91.807551 | E17: 69400 | F17: 526.89527 | G17: 78.340762 | H17: 55840 | I17: 420.3 | J17: 62.4 | K17: 49790 | L17: 373.3 | M17: 55.7 | N17: 51150 | O17: 384.1 | P17: 57.1 | Q17: 50990 | R17: 382.6 | S17: 56.8 | T17: 49400 | U17: 370.3 | V17: 54.2 | W17: 45150 | X17: 338.3 | Y17: 49.1 | Z17: 46350 | AA17: 348 | AB17: 45.4 | AC17: $7,001 - $8,000 | AD17: 46970 | AE17: 352.8 | AF17: 42 | AG17: 45640 | AH17: 343.1 | AI17: 37.6 | AJ17: 46440 | AK17: 349 | AL17: 35.1 | AM17: 42430 | AN17: 317.8 | AO17: 33.3 | AP17: 42630 | AQ17: 319.6 | AR17: 33.5 | AS17: 42610 | AT17: 319.4 | AU17: 33.5 | AV17: 40700 | AW17: 305.3 | AX17: 31.9 | AY17: 39620 | AZ17: 297.2 | BA17: 31.1 | BB17: 38260 | BC17: 287 | BD17: 30.1 | BE17: $7,001 - $8,000 | BF17: 37170 | BG17: 278.89 | BH17: 29.280585 | BI17: 35600 | BJ17: 267 | BK17: 28.033022 | BL17: 29550 | BM17: 220.8 | BN17: 23.182579 | BO17: 25260 | BP17: 189.37 | BQ17: 19.880627 | BR17: 27550 | BS17: 206.76 | BT17: 21.706567 | BU17: 27930 | BV17: 209.48 | BW17: 21.992846
A18: $8,001 - $9,000 | B18: 76880 | C18: 649.77809 | D18: 105.26851 | E18: 66770 | F18: 566.09663 | G18: 84.567337 | H18: 74850 | I18: 631.9 | J18: 94.7 | K18: 75090 | L18: 638.6 | M18: 95.7 | N18: 67390 | O18: 573.3 | P18: 86 | Q18: 64890 | R18: 553.2 | S18: 82.8 | T18: 63810 | U18: 547.6 | V18: 81.4 | W18: 49880 | X18: 424.6 | Y18: 62.2 | Z18: 46660 | AA18: 396.7 | AB18: 52.8 | AC18: $8,001 - $9,000 | AD18: 49630 | AE18: 422.2 | AF18: 51.2 | AG18: 46440 | AH18: 394.6 | AI18: 44 | AJ18: 44930 | AK18: 382.4 | AL18: 39.1 | AM18: 43490 | AN18: 370.2 | AO18: 38.8 | AP18: 42460 | AQ18: 361.3 | AR18: 37.9 | AS18: 41800 | AT18: 355 | AU18: 37.2 | AV18: 40940 | AW18: 348.1 | AX18: 36.5 | AY18: 40090 | AZ18: 340.9 | BA18: 35.7 | BB18: 39290 | BC18: 333.9 | BD18: 35.1 | BE18: $8,001 - $9,000 | BF18: 38210 | BG18: 324.72 | BH18: 34.089692 | BI18: 36590 | BJ18: 311.1 | BK18: 32.656408 | BL18: 28340 | BM18: 240.9 | BN18: 25.288163 | BO18: 26260 | BP18: 223.09 | BQ18: 23.422142 | BR18: 27480 | BS18: 233.68 | BT18: 24.533875 | BU18: 27310 | BV18: 232.06 | BW18: 24.365142
A19: $9,001 - $10,000 | B19: 115370 | C19: 1085.0339 | D19: 173.02153 | E19: 110070 | F19: 1050.2657 | G19: 158.82419 | H19: 91640 | I19: 875 | J19: 132.4 | K19: 62970 | L19: 603.2 | M19: 91.6 | N19: 53560 | O19: 508.2 | P19: 77.1 | Q19: 50620 | R19: 481.1 | S19: 73 | T19: 48330 | U19: 458.6 | V19: 69.2 | W19: 58080 | X19: 547 | Y19: 81.9 | Z19: 57730 | AA19: 545.9 | AB19: 74.1 | AC19: $9,001 - $10,000 | AD19: 64320 | AE19: 610.4 | AF19: 75.3 | AG19: 65530 | AH19: 623.8 | AI19: 70.9 | AJ19: 61140 | AK19: 584.4 | AL19: 60.5 | AM19: 58490 | AN19: 561.6 | AO19: 58.9 | AP19: 54710 | AQ19: 525.9 | AR19: 55.2 | AS19: 42900 | AT19: 409 | AU19: 42.9 | AV19: 42200 | AW19: 401.5 | AX19: 42 | AY19: 42060 | AZ19: 400.2 | BA19: 41.9 | BB19: 40510 | BC19: 385.4 | BD19: 40.5 | BE19: $9,001 - $10,000 | BF19: 38630 | BG19: 367.32 | BH19: 38.564028 | BI19: 37300 | BJ19: 354.7 | BK19: 37.234581 | BL19: 28980 | BM19: 275.5 | BN19: 28.923556 | BO19: 27380 | BP19: 260.25 | BQ19: 27.321317 | BR19: 27540 | BS19: 261.83 | BT19: 27.490687 | BU19: 27190 | BV19: 258.38 | BW19: 27.125485
A20: $10,001 - $11,000 | B20: 191540 | C20: 2026.4015 | D20: 322.55859 | E20: 77860 | F20: 819.73445 | G20: 128.48926 | H20: 91020 | I20: 955.2 | J20: 149.3 | K20: 88570 | L20: 922.6 | M20: 143.8 | N20: 90880 | O20: 948.5 | P20: 147.9 | Q20: 87890 | R20: 924.2 | S20: 144.7 | T20: 72840 | U20: 769.5 | V20: 120.3 | W20: 49160 | X20: 517 | Y20: 80.5 | Z20: 46080 | AA20: 483.8 | AB20: 67.1 | AC20: $10,001 - $11,000 | AD20: 47930 | AE20: 503.7 | AF20: 62.3 | AG20: 49210 | AH20: 516.6 | AI20: 58.8 | AJ20: 45480 | AK20: 476.4 | AL20: 49.6 | AM20: 41640 | AN20: 437.2 | AO20: 45.9 | AP20: 41450 | AQ20: 435.3 | AR20: 45.7 | AS20: 55480 | AT20: 578.3 | AU20: 60.7 | AV20: 52370 | AW20: 547.3 | AX20: 57.3 | AY20: 52070 | AZ20: 545.6 | BA20: 57.1 | BB20: 47590 | BC20: 498.3 | BD20: 52.3 | BE20: $10,001 - $11,000 | BF20: 47240 | BG20: 495.42 | BH20: 52.014721 | BI20: 45470 | BJ20: 478.6 | BK20: 50.246488 | BL20: 30940 | BM20: 324.7 | BN20: 34.091876 | BO20: 26900 | BP20: 282.27 | BQ20: 29.630419 | BR20: 27850 | BS20: 292.46 | BT20: 30.704438 | BU20: 27490 | BV20: 288.69 | BW20: 30.306395
... A180: Over $250,000 | B180: 5470 | C180: 2353.3 | D180: 870.1 | E180: 6600 | F180: 2982.6 | G180: 1105.5 | H180: 6800 | I180: 3151.3 | J180: 1169.9 | K180: 7980 | L180: 4131.2 | M180: 1541.5 | N180: 9150 | O180: 5272.1 | P180: 1976.2 | Q180: 10120 | R180: 4988 | S180: 1857 | T180: 11550 | U180: 5349 | V180: 1985.1 | W180: 13240 | X180: 5996.1 | Y180: 2222.9 | Z180: 13270 | AA180: 6559.5 | AB180: 2432.7 | AC180: $170,001 - $171,000 | AD180: 430 | AE180: 73.3 | AF180: 23.3 | AG180: 690 | AH180: 117.6 | AI180: 35 | AJ180: 640 | AK180: 109.2 | AL180: 30.2 | AM180: 710 | AN180: 121 | AO180: 33.5 | AP180: 570 | AQ180: 97.2 | AR180: 26.9 | AS180: 770 | AT180: 131.2 | AU180: 36.3 | AV180: 970 | AW180: 164.9 | AX180: 45.4 | AY180: 1090 | AZ180: 186 | BA180: 51.4 | BB180: 1230 | BC180: 209.4 | BD180: 57.9 | BE180: $170,001 - $171,000 | BF180: 1330 | BG180: 225.91 | BH180: 62.520566 | BI180: 1480 | BJ180: 252.7 | BK180: 69.919749 | BL180: 1630 | BM180: 277 | BN180: 76.659315 | BO180: 2380 | BP180: 405.36 | BQ180: 112.17575 | BR180: 2690 | BS180: 459.23 | BT180: 127.08513 | BU180: 3220 | BV180: 549.45 | BW180: 152.05213
AC181: $171,001 - $172,000 | AD181: 540 | AE181: 92.6 | AF181: 29.5 | AG181: 610 | AH181: 104.6 | AI181: 31.2 | AJ181: 690 | AK181: 118.3 | AL181: 32.8 | AM181: 630 | AN181: 108 | AO181: 29.9 | AP181: 750 | AQ181: 128.6 | AR181: 35.6 | AS181: 1040 | AT181: 178.4 | AU181: 49.4 | AV181: 1020 | AW181: 174.1 | AX181: 48.1 | AY181: 1040 | AZ181: 177.9 | BA181: 49.1 | BB181: 1080 | BC181: 185.7 | BD181: 51.5 | BE181: $171,001 - $172,000 | BF181: 1250 | BG181: 214.71 | BH181: 59.485525 | BI181: 1430 | BJ181: 244.6 | BK181: 67.759642 | BL181: 1540 | BM181: 263.3 | BN181: 72.938475 | BO181: 2010 | BP181: 344.53 | BQ181: 95.454342 | BR181: 2570 | BS181: 439.88 | BT181: 121.87102 | BU181: 2980 | BV181: 511.4 | BW181: 141.68536
A182: Total | B182: =SUM(B9:B180) -> 3012100 | C182: =SUM(C9:C180) -> 74084.827 | D182: =SUM(D9:D180) -> 16491.227 | E182: =SUM(E9:E180) -> 3076090 | F182: =SUM(F9:F180) -> 79229.585 | G182: =SUM(G9:G180) -> 17780.061 | H182: =SUM(H9:H180) -> 3130660 | I182: =SUM(I9:I180) -> 82746.6 | ... AB182: =SUM(AB9:AB180) -> 27638 | AC182: $172,001 - $173,000 | AD182: 320 | AE182: 55.2 | AF182: 17.6 | AG182: 510 | AH182: 87.9 | AI182: 26.2 | AJ182: 650 | AK182: 112.1 | AL182: 31.1 | AM182: 900 | AN182: 155.2 | AO182: 43.1 | AP182: 1140 | AQ182: 196.6 | AR182: 54.5 | AS182: 850 | AT182: 146.6 | AU182: 40.7 | AV182: 960 | AW182: 165.3 | AX182: 45.7 | AY182: 1020 | AZ182: 176.5 | BA182: 48.8 | BB182: 1050 | BC182: 181 | BD182: 50.2 | BE182: $172,001 - $173,000 | BF182: 1220 | BG182: 210.79 | BH182: 58.465576 | BI182: 1350 | BJ182: 232.4 | BK182: 64.454316 | BL182: 1580 | BM182: 272.4 | BN182: 75.548558 | BO182: 2070 | BP182: 356.37 | BQ182: 98.8442 | BR182: 2500 | BS182: 430.53 | BT182: 119.40991 | BU182: 3060 | BV182: 528.55 | BW182: 146.59947
AC183: $173,001 - $174,000 | AD183: 440 | AE183: 76.3 | AF183: 24.4 | AG183: 580 | AH183: 100.6 | AI183: 30 | AJ183: 440 | AK183: 76.4 | AL183: 21.2 | AM183: 970 | AN183: 168.3 | AO183: 46.7 | AP183: 1020 | AQ183: 177 | AR183: 49.1 | AS183: 650 | AT183: 112.8 | AU183: 31.3 | AV183: 890 | AW183: 154.9 | AX183: 42.9 | AY183: 990 | AZ183: 171.9 | BA183: 47.4 | BB183: 1080 | BC183: 187.5 | BD183: 52.1 | BE183: $173,001 - $174,000 | BF183: 1230 | BG183: 213.42 | BH183: 59.260868 | BI183: 1380 | BJ183: 239.6 | BK183: 66.530378 | BL183: 1520 | BM183: 262.8 | BN183: 72.982279 | BO183: 2060 | BP183: 358.12 | BQ183: 99.437381 | BR183: 2300 | BS183: 398.49 | BT183: 110.64656 | BU183: 2950 | BV183: 511.47 | BW183: 142.01582
AC184: $174,001 - $175,000 | AD184: 550 | AE184: 95.9 | AF184: 30.7 | AG184: 410 | AH184: 71.5 | AI184: 21.4 | AJ184: 620 | AK184: 108.2 | AL184: 30.1 | AM184: 920 | AN184: 160.6 | AO184: 44.6 | AP184: 760 | AQ184: 132.7 | AR184: 36.9 | AS184: 940 | AT184: 164.1 | AU184: 45.6 | AV184: 990 | AW184: 173 | AX184: 48 | AY184: 1100 | AZ184: 192.4 | BA184: 53.4 | BB184: 1160 | BC184: 201.6 | BD184: 56 | BE184: $174,001 - $175,000 | BF184: 1160 | BG184: 202.8 | BH184: 56.371764 | BI184: 1410 | BJ184: 246.3 | BK184: 68.456544 | BL184: 1530 | BM184: 267 | BN184: 74.224193 | BO184: 2140 | BP184: 373.84 | BQ184: 103.91656 | BR184: 2560 | BS184: 446.97 | BT184: 124.24716 | BU184: 3120 | BV184: 545 | BW184: 151.49419
AC185: $175,001 - $176,000 | AD185: 500 | AE185: 87.8 | AF185: 28.1 | AG185: 520 | AH185: 91.3 | AI185: 27.3 | AJ185: 470 | AK185: 82.5 | AL185: 22.9 | AM185: 870 | AN185: 152.7 | AO185: 42.5 | AP185: 770 | AQ185: 135.2 | AR185: 37.6 | AS185: 820 | AT185: 143.9 | AU185: 40 | AV185: 910 | AW185: 159.9 | AX185: 44.3 | AY185: 1000 | AZ185: 175.1 | BA185: 48.7 | BB185: 1050 | BC185: 184.6 | BD185: 51.4 | BE185: $175,001 - $176,000 | BF185: 1190 | BG185: 208.84 | BH185: 58.111106 | BI185: 1400 | BJ185: 245.3 | BK185: 68.268688 | BL185: 1520 | BM185: 266.4 | BN185: 74.12252 | BO185: 2280 | BP185: 400.77 | BQ185: 111.5156 | BR185: 2690 | BS185: 471.12 | BT185: 131.09 | BU185: 3240 | BV185: 567.83 | BW185: 158.00056
AC186: $176,001 - $177,000 | AD186: 390 | AE186: 68.8 | AF186: 22.1 | AG186: 420 | AH186: 74.2 | AI186: 22.2 | AJ186: 530 | AK186: 93.6 | AL186: 26.1 | AM186: 790 | AN186: 139.4 | AO186: 38.8 | AP186: 800 | AQ186: 141.2 | AR186: 39.3 | AS186: 890 | AT186: 157 | AU186: 43.7 | AV186: 910 | AW186: 160.8 | AX186: 44.7 | AY186: 980 | AZ186: 173 | BA186: 48 | BB186: 1100 | BC186: 193.4 | BD186: 53.9 | BE186: $176,001 - $177,000 | BF186: 1130 | BG186: 200.15 | BH186: 55.753069 | BI186: 1260 | BJ186: 223.1 | BK186: 62.145316 | BL186: 1490 | BM186: 262.5 | BN186: 73.107878 | BO186: 2100 | BP186: 369.94 | BQ186: 103.04773 | BR186: 2500 | BS186: 441.41 | BT186: 122.95636 | BU186: 3170 | BV186: 560.03 | BW186: 155.99858
AC187: $177,001 - $178,000 | AD187: 560 | AE187: 99.4 | AF187: 31.9 | AG187: 460 | AH187: 81.7 | AI187: 24.5 | AJ187: 830 | AK187: 147.3 | AL187: 41.1 | AM187: 520 | AN187: 92.3 | AO187: 25.7 | AP187: 610 | AQ187: 108.3 | AR187: 30.2 | AS187: 940 | AT187: 167 | AU187: 46.6 | AV187: 930 | AW187: 165.1 | AX187: 45.8 | AY187: 980 | AZ187: 174.2 | BA187: 48.4 | BB187: 1080 | BC187: 190.8 | BD187: 53.2 | BE187: $177,001 - $178,000 | BF187: 1080 | BG187: 191.7 | BH187: 53.453144 | BI187: 1280 | BJ187: 227.4 | BK187: 63.4046 | BL187: 1440 | BM187: 255.6 | BN187: 71.276843 | BO187: 2110 | BP187: 375.24 | BQ187: 104.6338 | BR187: 2480 | BS187: 440.21 | BT187: 122.75131 | BU187: 3150 | BV187: 559.69 | BW187: 156.06883
AC188: $178,001 - $179,000 | AD188: 440 | AE188: 78.5 | AF188: 25.2 | AG188: 250 | AH188: 44.6 | AI188: 13.4 | AJ188: 830 | AK188: 148.1 | AL188: 41.4 | AM188: 570 | AN188: 101.8 | AO188: 28.4 | AP188: 570 | AQ188: 101.8 | AR188: 28.4 | AS188: 990 | AT188: 176.8 | AU188: 49.3 | AV188: 1040 | AW188: 186 | AX188: 51.9 | AY188: 1090 | AZ188: 195.2 | BA188: 54.4 | BB188: 1000 | BC188: 179 | BD188: 50 | BE188: $178,001 - $179,000 | BF188: 1130 | BG188: 201.7 | BH188: 56.302232 | BI188: 1210 | BJ188: 216 | BK188: 60.285809 | BL188: 1380 | BM188: 245.8 | BN188: 68.605764 | BO188: 2220 | BP188: 395.77 | BQ188: 110.47238 | BR188: 2820 | BS188: 502.87 | BT188: 140.36986 | BU188: 3380 | BV188: 603.69 | BW188: 168.5079
AC189: $179,001 - $180,000 | AD189: 670 | AE189: 120.3 | AF189: 38.7 | AG189: 530 | AH189: 95.1 | AI189: 28.6 | AJ189: 450 | AK189: 80.8 | AL189: 22.6 | AM189: 710 | AN189: 127.4 | AO189: 35.6 | AP189: 710 | AQ189: 127.5 | AR189: 35.6 | AS189: 800 | AT189: 143.6 | AU189: 40.1 | AV189: 900 | AW189: 162.1 | AX189: 45.2 | AY189: 1110 | AZ189: 198.6 | BA189: 55.4 | BB189: 1120 | BC189: 200.2 | BD189: 55.9 | BE189: $179,001 - $180,000 | BF189: 1150 | BG189: 207.18 | BH189: 57.890891 | BI189: 1380 | BJ189: 248.3 | BK189: 69.387006 | BL189: 1690 | BM189: 304.2 | BN189: 85.007063 | BO189: 4200 | BP189: 753.79 | BQ189: 210.64889 | BR189: 5330 | BS189: 957.37 | BT189: 267.54367 | BU189: 7110 | BV189: 1277.1 | BW189: 356.90099
AC190: $180,001 - $181,000 | AD190: 430 | AE190: 77.6 | AF190: 25 | AG190: 280 | AH190: 50.6 | AI190: 15.2 | AJ190: 500 | AK190: 90.3 | AL190: 25.2 | AM190: 640 | AN190: 115.6 | AO190: 32.3 | AP190: 680 | AQ190: 122.8 | AR190: 34.3 | AS190: 690 | AT190: 124.4 | AU190: 34.8 | AV190: 810 | AW190: 146.9 | AX190: 41 | AY190: 920 | AZ190: 166.1 | BA190: 46.4 | BB190: 1050 | BC190: 189.5 | BD190: 53 | BE190: $180,001 - $181,000 | BF190: 1110 | BG190: 200.32 | BH190: 56.026816 | BI190: 1310 | BJ190: 236.1 | BK190: 66.022552 | BL190: 1550 | BM190: 280.3 | BN190: 78.381339 | BO190: 2850 | BP190: 513.14 | BQ190: 143.56461 | BR190: 3670 | BS190: 662.74 | BT190: 185.42831 | BU190: 4550 | BV190: 821.33 | BW190: 229.8067
AC191: $181,001 - $182,000 | AD191: 300 | AE191: 54.5 | AF191: 17.6 | AG191: 650 | AH191: 118 | AI191: 35.5 | AJ191: 550 | AK191: 99.8 | AL191: 27.9 | AM191: 750 | AN191: 136.1 | AO191: 38.1 | AP191: 710 | AQ191: 128.8 | AR191: 36.1 | AS191: 600 | AT191: 108.9 | AU191: 30.5 | AV191: 830 | AW191: 150.1 | AX191: 42 | AY191: 820 | AZ191: 147.9 | BA191: 41.3 | BB191: 960 | BC191: 175 | BD191: 49 | BE191: $181,001 - $182,000 | BF191: 1020 | BG191: 185.31 | BH191: 51.882969 | BI191: 1190 | BJ191: 216.5 | BK191: 60.621476 | BL191: 1290 | BM191: 233.2 | BN191: 65.296887 | BO191: 1760 | BP191: 318.88 | BQ191: 89.433982 | BR191: 2170 | BS191: 393.11 | BT191: 110.25367 | BU191: 2750 | BV191: 498.92 | BW191: 139.92983
AC192: $182,001 - $183,000 | AD192: 600 | AE192: 109.5 | AF192: 35.3 | AG192: 300 | AH192: 54.8 | AI192: 16.5 | AJ192: 570 | AK192: 104 | AL192: 29.1 | AM192: 430 | AN192: 78.5 | AO192: 22 | AP192: 670 | AQ192: 122.2 | AR192: 34.3 | AS192: 780 | AT192: 142.3 | AU192: 39.9 | AV192: 750 | AW192: 136.5 | AX192: 38.3 | AY192: 840 | AZ192: 154 | BA192: 43.1 | BB192: 900 | BC192: 163.3 | BD192: 45.8 | BE192: $182,001 - $183,000 | BF192: 1010 | BG192: 183.95 | BH192: 51.550887 | BI192: 1180 | BJ192: 214.4 | BK192: 60.091119 | BL192: 1220 | BM192: 221.7 | BN192: 62.135279 | BO192: 1690 | BP192: 308.77 | BQ192: 86.784666 | BR192: 1980 | BS192: 360.61 | BT192: 101.35483 | BU192: 2510 | BV192: 457.54 | BW192: 128.60225
AC193: $183,001 - $184,000 | AD193: 290 | AE193: 53.2 | AF193: 17.2 | AG193: 520 | AH193: 95.5 | AI193: 28.8 | AJ193: 620 | AK193: 113.8 | AL193: 31.9 | AM193: 450 | AN193: 82.5 | AO193: 23.1 | AP193: 780 | AQ193: 143.1 | AR193: 40.1 | AS193: 650 | AT193: 119.3 | AU193: 33.5 | AV193: 810 | AW193: 148.3 | AX193: 41.5 | AY193: 850 | AZ193: 155.3 | BA193: 43.5 | BB193: 890 | BC193: 163 | BD193: 45.7 | BE193: $183,001 - $184,000 | BF193: 1020 | BG193: 187.36 | BH193: 52.556747 | BI193: 1140 | BJ193: 209.6 | BK193: 58.784874 | BL193: 1200 | BM193: 219.3 | BN193: 61.510363 | BO193: 1520 | BP193: 279.64 | BQ193: 78.763931 | BR193: 1830 | BS193: 335.06 | BT193: 94.373033 | BU193: 2330 | BV193: 427.18 | BW193: 120.31801
AC194: $184,001 - $185,000 | AD194: 350 | AE194: 64.6 | AF194: 20.9 | AG194: 230 | AH194: 42.4 | AI194: 12.8 | AJ194: 470 | AK194: 86.7 | AL194: 24.3 | AM194: 190 | AN194: 35 | AO194: 9.8 | AP194: 700 | AQ194: 129.1 | AR194: 36.3 | AS194: 620 | AT194: 114.4 | AU194: 32.1 | AV194: 770 | AW194: 141.4 | AX194: 39.6 | AY194: 850 | AZ194: 156.6 | BA194: 44 | BB194: 910 | BC194: 168.3 | BD194: 47.2 | BE194: $184,001 - $185,000 | BF194: 1020 | BG194: 187.66 | BH194: 52.694183 | BI194: 1120 | BJ194: 207 | BK194: 58.125576 | BL194: 1190 | BM194: 219.6 | BN194: 61.655741 | BO194: 1540 | BP194: 283.98 | BQ194: 80.158811 | BR194: 1820 | BS194: 335.8 | BT194: 94.781616 | BU194: 2400 | BV194: 442.26 | BW194: 124.8272
... AC230: Over $300,000 | AD230: 9380 | AE230: 5213 | AF230: 1882.9 | AG230: 8260 | AH230: 4640.4 | AI230: 1566.7 | AJ230: 12050 | AK230: 6500.7 | AL230: 2035.8 | AM230: 14580 | AN230: 8500.9 | AO230: 2672.9 | AP230: 13570 | AQ230: 6876.5 | AR230: 2146 | AS230: 15020 | AT230: 7772 | AU230: 2428.4 | AV230: 18350 | AW230: 9730.7 | AX230: 3043.1 | AY230: 20040 | AZ230: 10722.4 | BA230: 3354.9 | BB230: 21970 | BC230: 11779.2 | BD230: 3687.7 | BE230: $300,000 - $350,000 | BF230: 7170 | BG230: 2317 | BH230: 699.49844 | BI230: 7570 | BJ230: 2443.7 | BK230: 737.74044 | BL230: 9200 | BM230: 2972.1 | BN230: 897.24609 | BO230: 9200 | BP230: 2969.37 | BQ230: 975.15823 | BR230: 10150 | BS230: 3276.82 | BT230: 1076.1365 | BU230: 11670 | BV230: 3767.81 | BW230: 1237.504
BE231: $350,001 - $400,000 | BF231: 4510 | BG231: 1685.08 | BH231: 515.10772 | BI231: 5040 | BJ231: 1883.2 | BK231: 575.66856 | BL231: 6200 | BM231: 2315.1 | BN231: 707.66441 | BO231: 5720 | BP231: 2133.85 | BQ231: 718.52781 | BR231: 6340 | BS231: 2362.6 | BT231: 795.45299 | BU231: 7100 | BV231: 2649.27 | BW231: 892.10686
BE232: $400,001 - $450,000 | BF232: 2790 | BG232: 1181.33 | BH232: 364.47695 | BI232: 3180 | BJ232: 1343.8 | BK232: 414.63176 | BL232: 4090 | BM232: 1731.1 | BN232: 534.11975 | BO232: 3640 | BP232: 1540.76 | BQ232: 528.59301 | BR232: 4020 | BS232: 1701.06 | BT232: 583.5175 | BU232: 4770 | BV232: 2016.99 | BW232: 691.87806
BE233: $450,001 - $500,000 | BF233: 2100 | BG233: 995.34 | BH233: 309.36599 | BI233: 2100 | BJ233: 995.5 | BK233: 309.44673 | BL233: 2950 | BM233: 1397.8 | BN233: 434.48093 | BO233: 2470 | BP233: 1173.89 | BQ233: 408.6322 | BR233: 2770 | BS233: 1310.32 | BT233: 456.03505 | BU233: 3160 | BV233: 1496.42 | BW233: 520.8019
BE234: $500,001 - $550,000 | BF234: 1400 | BG234: 734.01 | BH234: 229.49395 | BI234: 1590 | BJ234: 829.5 | BK234: 259.35752 | BL234: 2220 | BM234: 1161.4 | BN234: 363.13083 | BO234: 1780 | BP234: 932.74 | BQ234: 328.32155 | BR234: 2070 | BS234: 1083.5 | BT234: 381.4153 | BU234: 2290 | BV234: 1197.6 | BW234: 421.55855
BE235: $550,001 - $600,000 | BF235: 1120 | BG235: 642.8 | BH235: 201.95539 | BI235: 1210 | BJ235: 696.8 | BK235: 218.91387 | BL235: 1660 | BM235: 954.8 | BN235: 299.98262 | BO235: 1340 | BP235: 770.59 | BQ235: 273.86937 | BR235: 1530 | BS235: 880.69 | BT235: 312.97332 | BU235: 1680 | BV235: 961.14 | BW235: 341.54724
BE236: $600,001 - $650,000 | BF236: 840 | BG236: 522.67 | BH236: 164.87217 | BI236: 910 | BJ236: 570.5 | BK236: 179.97985 | BL236: 1400 | BM236: 873.3 | BN236: 275.49064 | BO236: 980 | BP236: 613.51 | BQ236: 219.72714 | BR236: 1050 | BS236: 654.42 | BT236: 234.36807 | BU236: 1310 | BV236: 817.32 | BW236: 292.71118
BE237: $650,001 - $700,000 | BF237: 650 | BG237: 436.39 | BH237: 138.13304 | BI237: 720 | BJ237: 484.9 | BK237: 153.48316 | BL237: 1100 | BM237: 741.9 | BN237: 234.83139 | BO237: 840 | BP237: 564.13 | BQ237: 203.35031 | BR237: 940 | BS237: 634.51 | BT237: 228.75239 | BU237: 1020 | BV237: 688.54 | BW237: 248.23118
BE238: $700,001 - $750,000 | BF238: 550 | BG238: 394 | BH238: 125.07009 | BI238: 530 | BJ238: 380.9 | BK238: 120.93172 | BL238: 950 | BM238: 688.7 | BN238: 218.64559 | BO238: 610 | BP238: 443.09 | BQ238: 160.64006 | BR238: 670 | BS238: 487.64 | BT238: 176.78034 | BU238: 850 | BV238: 614.04 | BW238: 222.61681
BE239: $750,001 - $800,000 | BF239: 430 | BG239: 329.47 | BH239: 104.857 | BI239: 460 | BJ239: 353.7 | BK239: 112.57497 | BL239: 770 | BM239: 591.6 | BN239: 188.29105 | BO239: 530 | BP239: 410.42 | BQ239: 149.5292 | BR239: 530 | BS239: 407.07 | BT239: 148.29873 | BU239: 690 | BV239: 536.1 | BW239: 195.30402
BE240: $800,001 - $850,000 | BF240: 330 | BG240: 272.47 | BH240: 86.911049 | BI240: 390 | BJ240: 317.8 | BK240: 101.36695 | BL240: 700 | BM240: 578.6 | BN240: 184.56604 | BO240: 450 | BP240: 370.86 | BQ240: 135.68875 | BR240: 530 | BS240: 436.68 | BT240: 159.76743 | BU240: 530 | BV240: 433.11 | BW240: 158.457
BE241: $850,001 - $900,000 | BF241: 290 | BG241: 254.58 | BH241: 81.370767 | BI241: 330 | BJ241: 291.1 | BK241: 93.028662 | BL241: 500 | BM241: 436.2 | BN241: 139.4156 | BO241: 350 | BP241: 307.11 | BQ241: 112.79659 | BR241: 350 | BS241: 306.95 | BT241: 112.73134 | BU241: 480 | BV241: 417.43 | BW241: 153.31465
BE242: $900,001 - $950,000 | BF242: 230 | BG242: 216.17 | BH242: 69.21261 | BI242: 240 | BJ242: 221.9 | BK242: 71.045955 | BL242: 490 | BM242: 456 | BN242: 146.00176 | BO242: 350 | BP242: 326.41 | BQ242: 120.28388 | BR242: 290 | BS242: 265.41 | BT242: 97.804313 | BU242: 320 | BV242: 298.33 | BW242: 109.92863
... BE244: Over $1,000,000 | BF244: 1610 | BG244: 2869.91 | BH244: 932.45015 | BI244: 1840 | BJ244: 3331.3 | BK244: 1082.6072 | BL244: 4570 | BM244: 10379.2 | BN244: 3383.6117 | BO244: 2090 | BP244: 3849.34 | BQ244: 1459.6339 | BR244: 2150 | BS244: 3985.42 | BT244: 1511.4927 | BU244: 2690 | BV244: 5150.97 | BW244: 1955.4396
AC246: Total | AD246: =SUM(AD8:AD230) -> 3443350 | AE246: =SUM(AE8:AE230) -> 118338 | AF246: =SUM(AF8:AF230) -> 25337.9 | AG246: =SUM(AG8:AG230) -> 3449800 | AH246: =SUM(AH8:AH230) -> 121370.2 | AI246: =SUM(AI8:AI230) -> 24202.1 | AJ246: =SUM(AJ8:AJ230) -> 3472950 | AK246: =SUM(AK8:AK230) -> 130431.7 | ... BD246: =SUM(BD8:BD230) -> 35671.1 | BE246: Total | BF246: =SUM(BF8:BF244) -> 4239750 | BG246: =SUM(BG8:BG244) -> 187284.01 | BH246: =SUM(BH8:BH244) -> 38354.404 | BI246: =SUM(BI8:BI244) -> 4336140 | BJ246: =SUM(BJ8:BJ244) -> 199737.7 | BK246: =SUM(BK8:BK244) -> 41462.671 | BL246: =SUM(BL8:BL244) -> 4334730 | BM246: =SUM(BM8:BM244) -> 217897 | ... BW246: =SUM(BW8:BW244) -> 60676.798
BE249: Decile* | BF249: 2019 | BI249: 2020 | BL249: 2021 | BO249: 2022 | BR249: 2023 | BU249: 2024
BF250: Income at upper boundary ($) | BG250: Taxable Income ($M) | BH250: Tax on Taxable Income ($M) | BI250: Income at upper boundary ($) | BJ250: Taxable Income ($M) | BK250: Tax on Taxable Income ($M) | BL250: Income at upper boundary ($) | BM250: Taxable Income ($M) | BN250: Tax on Taxable Income ($M) | BO250: Income at upper boundary ($) | BP250: Taxable Income ($M) | BQ250: Tax on Taxable Income ($M) | BR250: Income at upper boundary ($) | BS250: Taxable Income ($M) | BT250: Tax on Taxable Income ($M) | BU250: Income at upper boundary ($) | BV250: Taxable Income ($M) | BW250: Tax on Taxable Income ($M)
BE253: 1 | BF253: 290 | BG253: 10.3 | BH253: 1 | BI253: 250 | BJ253: 8.7 | BK253: 0.8 | BL253: 191 | BM253: 5.3 | BN253: 0.5 | BO253: 328 | BP253: 9.3 | BQ253: 0.9 | BR253: 286 | BS253: 13.7 | BT253: 1.4 | BU253: 423 | BV253: 24.1 | BW253: 2.5
BE254: 2 | BF254: 9597 | BG254: 1832.6 | BH254: 192.4 | BI254: 10149 | BJ254: 1961.2 | BK254: 205.9 | BL254: 12419 | BM254: 2511.5 | BN254: 263.7 | BO254: 14133 | BP254: 3025.3 | BQ254: 317.6 | BR254: 13614 | BS254: 2697 | BT254: 283.1 | BU254: 14310 | BV254: 2967.1 | BW254: 311.6
BE255: 3 | BF255: 17385 | BG255: 5810.8 | BH255: 634.8 | BI255: 18426 | BJ255: 6222.9 | BK255: 689.9 | BL255: 19358 | BM255: 7138.2 | BN255: 828.3 | BO255: 20128 | BP255: 7939.5 | BQ255: 961 | BR255: 21425 | BS255: 8657.4 | BT255: 1063.4 | BU255: 23052 | BV255: 9414.5 | BW255: 1184.9
BE256: 4 | BF256: 22462 | BG256: 8328.2 | BH256: 1041.9 | BI256: 23702 | BJ256: 9011.6 | BK256: 1152 | BL256: 25120 | BM256: 9497.5 | BN256: 1228.2 | BO256: 26343 | BP256: 10229.1 | BQ256: 1344.2 | BR256: 27947 | BS256: 10973.8 | BT256: 1452.8 | BU256: 30074 | BV256: 12017 | BW256: 1611.4
BE257: 5 | BF257: 30296 | BG257: 10943.1 | BH257: 1441.3 | BI257: 31899 | BJ257: 11822.9 | BK257: 1573.4 | BL257: 33775 | BM257: 12329.8 | BN257: 1663.4 | BO257: 36849 | BP257: 13298.2 | BQ257: 1818.8 | BR257: 37625 | BS257: 14349.9 | BT257: 1992.9 | BU257: 40573 | BV257: 16480.6 | BW257: 2327.9
BE258: 6 | BF258: 41933 | BG258: 15324.3 | BH258: 2134.8 | BI258: 43998 | BJ258: 16482.5 | BK258: 2323.3 | BL258: 46108 | BM258: 17380.4 | BN258: 2488.3 | BO258: 49692 | BP258: 19066.9 | BQ258: 2821 | BR258: 51825 | BS258: 20449.3 | BT258: 3089.8 | BU258: 54970 | BV258: 22480.7 | BW258: 3526.7
BE259: 7 | BF259: 53136 | BG259: 20118.4 | BH259: 3108.6 | BI259: 55519 | BJ259: 21511.8 | BK259: 3437.2 | BL259: 57669 | BM259: 22399.2 | BN259: 3696.7 | BO259: 61988 | BP259: 24338.8 | BQ259: 4250.6 | BR259: 65343 | BS259: 26586.1 | BT259: 4802.5 | BU259: 69211 | BV259: 29095.6 | BW259: 5452.3
BE260: 8 | BF260: 68134 | BG260: 25518.7 | BH260: 4696.2 | BI260: 70050 | BJ260: 27170.4 | BK260: 5124.5 | BL260: 72276 | BM260: 28094.6 | BN260: 5404.6 | BO260: 77148 | BP260: 30232.8 | BQ260: 6037.3 | BR260: 81648 | BS260: 33138.1 | BT260: 6817.6 | BU260: 86733 | BV260: 36196 | BW260: 7683
BE261: 9 | BF261: 91063 | BG261: 33000.4 | BH261: 7041.7 | BI261: 94780 | BJ261: 35015 | BK261: 7617.7 | BL261: 98788 | BM261: 36327.2 | BN261: 8052.1 | BO261: 105078 | BP261: 39042.1 | BQ261: 8915 | BR261: 111159 | BS261: 42946.2 | BT261: 10044.3 | BU261: 119404 | BV261: 47373.9 | BW261: 11371.4
BE262: 10 | BG262: 66397.4 | BH262: 18061.5 | BJ262: 70530.4 | BK262: 19337.9 | BM262: 82213.5 | BN262: 23194.6 | BP262: 77581.5 | BQ262: 22494.4 | BS262: 83684.4 | BT262: 24430.4 | BV262: 91939.2 | BW262: 27205.2
BE264: Top 10%** | BF264: 2019 | BI264: 2020 | BL264: 2021 | BO264: 2022 | BR264: 2023 | BU264: 2024
BF265: Income at upper boundary ($) | BG265: Taxable Income ($M) | BH265: Tax on Taxable Income ($M) | BI265: Income at upper boundary ($) | BJ265: Taxable Income ($M) | BK265: Tax on Taxable Income ($M) | BL265: Income at upper boundary ($) | BM265: Taxable Income ($M) | BN265: Tax on Taxable Income ($M) | BO265: Income at upper boundary ($) | BP265: Taxable Income ($M) | BQ265: Tax on Taxable Income ($M) | BR265: Income at upper boundary ($) | BS265: Taxable Income ($M) | BT265: Tax on Taxable Income ($M) | BU265: Income at upper boundary ($) | BV265: Taxable Income ($M) | BW265: Tax on Taxable Income ($M)
BE268: 91 | BF268: 95039 | BG268: 3942.9 | BH268: 916.2 | BI268: 98965 | BJ268: 4196.6 | BK268: 991.2 | BL268: 103144 | BM268: 4372.9 | BN268: 1049.4 | BO268: 109904 | BP268: 4695.5 | BQ268: 1152.6 | BR268: 116222 | BS268: 5165.5 | BT268: 1291.8 | BU268: 124724 | BV268: 5724.4 | BW268: 1462.9
BE269: 92 | BF269: 99788 | BG269: 4128.3 | BH269: 977.3 | BI269: 103712 | BJ269: 4389.1 | BK269: 1054.7 | BL269: 108441 | BM269: 4581.3 | BN269: 1118.3 | BO269: 115527 | BP269: 4922.5 | BQ269: 1227.6 | BR269: 121992 | BS269: 5413.1 | BT269: 1373.5 | BU269: 130845 | BV269: 5994.5 | BW269: 1552
BE270: 93 | BF270: 105228 | BG270: 4339 | BH270: 1047 | BI270: 109703 | BJ270: 4622.3 | BK270: 1131.6 | BL270: 114787 | BM270: 4832.7 | BN270: 1201.2 | BO270: 122057 | BP270: 5190.5 | BQ270: 1316 | BR270: 128800 | BS270: 5695.6 | BT270: 1466.7 | BU270: 138091 | BV270: 6306.1 | BW270: 1654.8
BE271: 94 | BF271: 112227 | BG271: 4606.1 | BH271: 1135 | BI271: 116999 | BJ271: 4907.3 | BK271: 1225.7 | BL271: 122357 | BM271: 5133.6 | BN271: 1300.6 | BO271: 130125 | BP271: 5505.9 | BQ271: 1420.1 | BR271: 137118 | BS271: 6037.2 | BT271: 1579.5 | BU271: 146709 | BV271: 6677.4 | BW271: 1777.3
BE272: 95 | BF272: 121000 | BG272: 4938.9 | BH272: 1244.8 | BI272: 125863 | BJ272: 5258.8 | BK272: 1341.7 | BL272: 132245 | BM272: 5509 | BN272: 1424.4 | BO272: 140306 | BP272: 5901.6 | BQ272: 1550.7 | BR272: 147480 | BS272: 6459.7 | BT272: 1718.9 | BU272: 157130 | BV272: 7121.2 | BW272: 1923.8
BE273: 96 | BF273: 132482 | BG273: 5359.9 | BH273: 1383.9 | BI273: 137934 | BJ273: 5706.5 | BK273: 1489.4 | BL273: 145503 | BM273: 6004.7 | BN273: 1588 | BO273: 153422 | BP273: 6408.5 | BQ273: 1717.9 | BR273: 160535 | BS273: 6985.1 | BT273: 1892.3 | BU273: 170384 | BV273: 7674.5 | BW273: 2106.4
BE274: 97 | BF274: 149198 | BG274: 5948.7 | BH274: 1578.1 | BI274: 154651 | BJ274: 6322.3 | BK274: 1692.6 | BL274: 164511 | BM274: 6688.7 | BN274: 1813.7 | BO274: 171342 | BP274: 7076.9 | BQ274: 1938.5 | BR274: 177806 | BS274: 7679.3 | BT274: 2121.4 | BU274: 184322 | BV274: 8329.6 | BW274: 2324
BE275: 98 | BF275: 175967 | BG275: 6832.9 | BH275: 1869.9 | BI275: 182169 | BJ275: 7248.2 | BK275: 1998.2 | BL275: 196459 | BM275: 7748 | BN275: 2163.3 | BO275: 195507 | BP275: 7946.8 | BQ275: 2235.1 | BR275: 202046 | BS275: 8532 | BT275: 2424.2 | BU275: 212221 | BV275: 9240.6 | BW275: 2670.7
BE276: 99 | BF276: 234060 | BG276: 8488.4 | BH276: 2416.2 | BI276: 241590 | BJ276: 8971.2 | BK276: 2566.8 | BL276: 276114 | BM276: 9890.9 | BN276: 2870.4 | BO276: 257402 | BP276: 9656.5 | BQ276: 2897.1 | BR276: 264179 | BS276: 10351 | BT276: 3133.1 | BU276: 277493 | BV276: 11217.2 | BW276: 3441.6
BE277: 100 | BG277: 17812.4 | BH277: 5493.1 | BJ277: 18908.1 | BK277: 5845.9 | BM277: 27451.6 | BN277: 8665.5 | BP277: 20276.7 | BQ277: 7039 | BS277: 21365.9 | BT277: 7428.9 | BV277: 23653.6 | BW277: 8291.8
BE279: * Each decile contains the population divided by 10
BE280: ** Each percentile for the 10% of income earners contains the population divided by 100
BE282: Income from individuals from 2019 to 2024 by Age Band
BF285: 2019 | BI285: 2020 | BL285: 2021 | BO285: 2022 | BR285: 2023 | BU285: 2024
BE286: Age Bands | BF286: Number of People | BG286: Taxable Income ($M) | BH286: Tax on Taxable Income ($M) | BI286: Number of People | BJ286: Taxable Income ($M) | BK286: Tax on Taxable Income ($M) | BL286: Number of People | BM286: Taxable Income ($M) | BN286: Tax on Taxable Income ($M) | BO286: Number of People | BP286: Taxable Income ($M) | BQ286: Tax on Taxable Income ($M) | BR286: Number of People | BS286: Taxable Income ($M) | BT286: Tax on Taxable Income ($M) | BU286: Number of People | BV286: Taxable Income ($M) | BW286: Tax on Taxable Income ($M)
BE289: Under 15 | BF289: 217240 | BG289: 111.5 | BH289: 18.3 | BI289: 211620 | BJ289: 65.3 | BK289: 7.7 | BL289: 210990 | BM289: 60.8 | BN289: 7 | BO289: 205900 | BP289: 65 | BQ289: 7.4 | BR289: 212510 | BS289: 87.2 | BT289: 10.1 | BU289: 206040 | BV289: 100.7 | BW289: 12.1
BE290: 15-19 | BF290: 243200 | BG290: 2423.1 | BH290: 306.7 | BI290: 241780 | BJ290: 2554.7 | BK290: 326.3 | BL290: 233840 | BM290: 2573.1 | BN290: 334.6 | BO290: 246840 | BP290: 3051.2 | BQ290: 401.6 | BR290: 269090 | BS290: 3743.5 | BT290: 504.5 | BU290: 269190 | BV290: 3766.2 | BW290: 521
BE291: 20-24 | BF291: 357960 | BG291: 9312.4 | BH291: 1380.1 | BI291: 357110 | BJ291: 9719.4 | BK291: 1466.6 | BL291: 334370 | BM291: 9926 | BN291: 1523.5 | BO291: 324860 | BP291: 10874.6 | BQ291: 1737.9 | BR291: 335050 | BS291: 11849.5 | BT291: 1963.1 | BU291: 350820 | BV291: 12515.4 | BW291: 2116.1
BE292: 25-29 | BF292: 412920 | BG292: 15673.4 | BH292: 2749.9 | BI292: 417430 | BJ292: 16608.8 | BK292: 2976.1 | BL292: 390960 | BM292: 17163.6 | BN292: 3149.6 | BO292: 372460 | BP292: 18273.9 | BQ292: 3500.2 | BR292: 384180 | BS292: 19162.8 | BT292: 3759.7 | BU292: 402280 | BV292: 20054.5 | BW292: 3985.9
BE293: 30-34 | BF293: 370140 | BG293: 17146.1 | BH293: 3362.6 | BI293: 391350 | BJ293: 18846.3 | BK293: 3759.4 | BL293: 396610 | BM293: 20678.8 | BN293: 4219.7 | BO293: 403310 | BP293: 22752.5 | BQ293: 4774.2 | BR293: 425300 | BS293: 24535.3 | BT293: 5257.1 | BU293: 450080 | BV293: 26911.5 | BW293: 5860.7
BE294: 35-39 | BF294: 327720 | BG294: 17750.3 | BH294: 3752 | BI294: 343880 | BJ294: 19317.9 | BK294: 4144.2 | BL294: 349870 | BM294: 21306.7 | BN294: 4691 | BO294: 358390 | BP294: 22907.4 | BQ294: 5149.6 | BR294: 385240 | BS294: 25089.3 | BT294: 5723.1 | BU294: 415510 | BV294: 28263.5 | BW294: 6541.8
BE295: 40-44 | BF295: 304890 | BG295: 18696.5 | BH295: 4131.3 | BI295: 312720 | BJ295: 19767.5 | BK295: 4419.4 | BL295: 317610 | BM295: 21755.2 | BN295: 4995.2 | BO295: 324360 | BP295: 22896.9 | BQ295: 5372.8 | BR295: 345610 | BS295: 25072 | BT295: 5984.2 | BU295: 368310 | BV295: 27828.2 | BW295: 6733.7
BE296: 45-49 | BF296: 332770 | BG296: 21781.7 | BH296: 4911.6 | BI296: 334800 | BJ296: 22774.6 | BK296: 5209.5 | BL296: 328400 | BM296: 24371.7 | BN296: 5738.3 | BO296: 321720 | BP296: 24289.9 | BQ296: 5846.1 | BR296: 324210 | BS296: 25489.1 | BT296: 6247.5 | BU296: 329580 | BV296: 27115.2 | BW296: 6746
BE297: 50-54 | BF297: 316970 | BG297: 20679.5 | BH297: 4661.4 | BI297: 323280 | BJ297: 21891 | BK297: 5003.9 | BL297: 329140 | BM297: 24319.3 | BN297: 5729.8 | BO297: 334750 | BP297: 25099.6 | BQ297: 6053.7 | BR297: 343000 | BS297: 26943.6 | BT297: 6611.7 | BU297: 345160 | BV297: 28856.4 | BW297: 7221.6
BE298: 55-59 | BF298: 313470 | BG298: 19517.7 | BH298: 4353.3 | BI298: 318870 | BJ298: 20501.1 | BK298: 4629 | BL298: 320910 | BM298: 22571.4 | BN298: 5273.8 | BO298: 319190 | BP298: 22301.1 | BQ298: 5288.8 | BR298: 319720 | BS298: 23550.1 | BT298: 5687.5 | BU298: 321280 | BV298: 25397.1 | BW298: 6269.9
BE299: 60-64 | BF299: 268710 | BG299: 14718.3 | BH299: 3193.8 | BI299: 279360 | BJ299: 15914.8 | BK299: 3502.2 | BL299: 290020 | BM299: 18215.4 | BN299: 4176.1 | BO299: 298490 | BP299: 18300.7 | BQ299: 4218.9 | BR299: 309320 | BS299: 19963.1 | BT299: 4674.1 | BU299: 315160 | BV299: 22157 | BW299: 5320.8
BE300: 65-69 | BF300: 237800 | BG300: 11653.4 | BH300: 2411.7 | BI300: 243930 | BJ300: 12407.4 | BK300: 2596.4 | BL300: 251010 | BM300: 13858.3 | BN300: 3040.3 | BO300: 257770 | BP300: 13556.2 | BQ300: 2945.6 | BR300: 266800 | BS300: 15008.7 | BT300: 3328.3 | BU300: 274900 | BV300: 17431.3 | BW300: 4007.9
... BE303: Unknown | BF303: 5290 | BG303: 352.3 | BH303: 83.7 | BI303: 5890 | BJ303: 354.2 | BK303: 83.6 | BL303: 5310 | BM303: 516.4 | BN303: 139 | BO303: 5290 | BP303: 342.2 | BQ303: 84.6 | BR303: 5060 | BS303: 335.3 | BT303: 82.9 | BU303: 4990 | BV303: 368.1 | BW303: 93.7
BE305: Total | BF305: =SUM(BF289:BF303) -> 4239750 | BG305: =SUM(BG289:BG303) -> 187284.1 | BH305: =SUM(BH289:BH303) -> 38354.5 | BI305: =SUM(BI289:BI303) -> 4336140 | BJ305: =SUM(BJ289:BJ303) -> 199737.4 | BK305: =SUM(BK289:BK303) -> 41462.7 | BL305: =SUM(BL289:BL303) -> 4334630 | BM305: =SUM(BM289:BM303) -> 217897.2 | ... BW305: =SUM(BW289:BW303) -> 60676.9

Sheet Age by income band distribution
A1: 2024 income distribution by age band and income band (Number of people)
B3: Age Band
A4: Taxable Income | B4: Unknown | C4: Under 15 | D4: 15-19 | E4: 20-24 | F4: 25-29 | G4: 30-34 | H4: 35-39 | I4: 40-44 | J4: 45-49 | K4: 50-54 | L4: 55-59 | M4: 60-64 | N4: 65-69 | O4: 70-74 | P4: 75+
A5: bands to $180,000
A6: nil | B6: 290 | C6: 2060 | D6: 480 | E6: 910 | F6: 2770 | G6: 5320 | H6: 6480 | I6: 6200 | J6: 5160 | K6: 5690 | L6: 5630 | M6: 6220 | N6: 3180 | O6: 2120 | P6: 2310
A7: $0.01 - $100 | B7: 240 | C7: 140490 | D7: 41370 | E7: 10070 | F7: 16900 | G7: 22730 | H7: 22270 | I7: 18630 | J7: 13670 | K7: 12040 | L7: 10470 | M7: 9860 | N7: 4760 | O7: 3240 | P7: 4290
A8: $101 - $1,000 | B8: 150 | C8: 46320 | D8: 23380 | E8: 6810 | F8: 7760 | G8: 9170 | H8: 8430 | I8: 6970 | J8: 5250 | K8: 5200 | L8: 5120 | M8: 6090 | N8: 2390 | O8: 1650 | P8: 2290
A9: $1,001 - $2,000 | B9: 40 | C9: 8000 | D9: 13690 | E9: 4670 | F9: 4110 | G9: 3990 | H9: 3420 | I9: 2960 | J9: 2230 | K9: 2160 | L9: 2280 | M9: 2770 | N9: 1130 | O9: 770 | P9: 1510
A10: $2,001 - $3,000 | B10: 30 | C10: 2620 | D10: 10790 | E10: 4020 | F10: 3350 | G10: 2990 | H10: 2620 | I10: 2120 | J10: 1580 | K10: 1640 | L10: 1660 | M10: 2220 | N10: 880 | O10: 550 | P10: 1250
A11: $3,001 - $4,000 | B11: 20 | C11: 1360 | D11: 9390 | E11: 4030 | F11: 3050 | G11: 2710 | H11: 2190 | I11: 1790 | J11: 1440 | K11: 1400 | L11: 1490 | M11: 1880 | N11: 780 | O11: 510 | P11: 1170
A12: $4,001 - $5,000 | B12: 10 | C12: 920 | D12: 8740 | E12: 4000 | F12: 2890 | G12: 2520 | H12: 2150 | I12: 1630 | J12: 1230 | K12: 1280 | L12: 1380 | M12: 1720 | N12: 740 | O12: 490 | P12: 1180
A13: $5,001 - $6,000 | B13: 20 | C13: 660 | D13: 8320 | E13: 4070 | F13: 2890 | G13: 2360 | H13: 2020 | I13: 1560 | J13: 1200 | K13: 1180 | L13: 1270 | M13: 1670 | N13: 710 | O13: 390 | P13: 1190
A14: $6,001 - $7,000 | B14: 20 | C14: 540 | D14: 8020 | E14: 3970 | F14: 2740 | G14: 2260 | H14: 1830 | I14: 1480 | J14: 1130 | K14: 1110 | L14: 1190 | M14: 1590 | N14: 710 | O14: 420 | P14: 1190
A15: $7,001 - $8,000 | B15: 10 | C15: 540 | D15: 7550 | E15: 4030 | F15: 2740 | G15: 2410 | H15: 1840 | I15: 1560 | J15: 1180 | K15: 1110 | L15: 1180 | M15: 1530 | N15: 690 | O15: 420 | P15: 1120
A16: $8,001 - $9,000 | B16: 10 | C16: 350 | D16: 7180 | E16: 4030 | F16: 2830 | G16: 2250 | H16: 1850 | I16: 1500 | J16: 1210 | K16: 1150 | L16: 1190 | M16: 1530 | N16: 710 | O16: 430 | P16: 1100
A17: $9,001 - $10,000 | B17: 20 | C17: 320 | D17: 6870 | E17: 4330 | F17: 2620 | G17: 2260 | H17: 1870 | I17: 1440 | J17: 1150 | K17: 1120 | L17: 1230 | M17: 1610 | N17: 730 | O17: 430 | P17: 1220
... A188: Over $180,000 | B188: 340 | C188: 10 | D188: 20 | E188: 200 | F188: 1860 | G188: 7890 | H188: 15920 | I188: 21320 | J188: 23780 | K188: 25760 | L188: 21200 | M188: 16060 | N188: 10740 | O188: 4500 | P188: 4130
A189: All | B189: =SUM(B6:B188) -> 5050 | C189: =SUM(C6:C188) -> 206020 | D189: =SUM(D6:D188) -> 269190 | E189: =SUM(E6:E188) -> 350890 | F189: =SUM(F6:F188) -> 402340 | G189: =SUM(G6:G188) -> 450130 | H189: =SUM(H6:H188) -> 415610 | I189: =SUM(I6:I188) -> 368410 | ... P189: =SUM(P6:P188) -> 411850

Sheet Hidden Graph Data
B1: Number of individuals | F1: Aggregate taxable income | J1: Aggregate tax assessed | Q1: Taxable Income | R1: Age Band
A2: Band | B2: 2004 | C2: 2014 | D2: 2023 | E2: 2024 | F2: 2004 | G2: 2014 | H2: 2023 | I2: 2024 | J2: 2004 | K2: 2014 | L2: 2023 | M2: 2024 | Q2: bands to $1,000,000 | R2: Unknown | S2: 0-14 | T2: 15-24 | U2: 25-34 | V2: 35-44 | W2: 45-54 | X2: 55-64 | Y2: 65+
A3: 0 | Q3: nil | R3: ='Age by income band distribution'!B6 -> 290 | S3: ='Age by income band distribution'!C6 -> 2060 | T3: ='Age by income band distribution'!D6+'Age by income band distribution'!E6 -> 1390 | U3: ='Age by income band distribution'!F6+'Age by income band distribution'!G6 -> 8090 | V3: ='Age by income band distribution'!H6+'Age by income band distribution'!I6 -> 12680 | W3: ='Age by income band distribution'!J6+'Age by income band distribution'!K6 -> 10850 | X3: ='Age by income band distribution'!L6+'Age by income band distribution'!M6 -> 11850 | Y3: ='Age by income band distribution'!N6+'Age by income band distribution'!O6+'Age by income band distribution'!P6 -> 7610
A4: 1000 | B4: ='Income tables 2001-24'!K10 -> 101730 | C4: ='Income tables 2001-24'!AP10 -> 83060 | D4: ='Income tables 2001-24'!BR10 -> 112490 | E4: ='Income tables 2001-24'!BU10 -> 136970 | F4: ='Income tables 2001-24'!L10 -> 46.9 | G4: ='Income tables 2001-24'!AQ10 -> 39.7 | H4: ='Income tables 2001-24'!BS10 -> 47.12 | I4: ='Income tables 2001-24'!BV10 -> 55.76 | J4: ='Income tables 2001-24'!M10 -> 6.2 | K4: ='Income tables 2001-24'!AR10 -> 4.2 | L4: ='Income tables 2001-24'!BT10 -> 4.9453852 | M4: ='Income tables 2001-24'!BW10 -> 5.8526859 | Q4: $0.01 - $100 | R4: ='Age by income band distribution'!B7 -> 240 | S4: ='Age by income band distribution'!C7 -> 140490 | T4: ='Age by income band distribution'!D7+'Age by income band distribution'!E7 -> 51440 | U4: ='Age by income band distribution'!F7+'Age by income band distribution'!G7 -> 39630 | V4: ='Age by income band distribution'!H7+'Age by income band distribution'!I7 -> 40900 | W4: ='Age by income band distribution'!J7+'Age by income band distribution'!K7 -> 25710 | X4: ='Age by income band distribution'!L7+'Age by income band distribution'!M7 -> 20330 | Y4: ='Age by income band distribution'!N7+'Age by income band distribution'!O7+'Age by income band distribution'!P7 -> 12290
A5: 2000 | B5: ='Income tables 2001-24'!K11 -> 69610 | C5: ='Income tables 2001-24'!AP11 -> 58080 | D5: ='Income tables 2001-24'!BR11 -> 49700 | E5: ='Income tables 2001-24'!BU11 -> 53720 | F5: ='Income tables 2001-24'!L11 -> 103.4 | G5: ='Income tables 2001-24'!AQ11 -> 86.5 | H5: ='Income tables 2001-24'!BS11 -> 72.19 | I5: ='Income tables 2001-24'!BV11 -> 77.71 | J5: ='Income tables 2001-24'!M11 -> 13.9 | K5: ='Income tables 2001-24'!AR11 -> 9.1 | L5: ='Income tables 2001-24'!BT11 -> 7.5764595 | M5: ='Income tables 2001-24'!BW11 -> 8.1575698 | Q5: $101 - $1,000 | R5: ='Age by income band distribution'!B8 -> 150 | S5: ='Age by income band distribution'!C8 -> 46320 | T5: ='Age by income band distribution'!D8+'Age by income band distribution'!E8 -> 30190 | U5: ='Age by income band distribution'!F8+'Age by income band distribution'!G8 -> 16930 | V5: ='Age by income band distribution'!H8+'Age by income band distribution'!I8 -> 15400 | W5: ='Age by income band distribution'!J8+'Age by income band distribution'!K8 -> 10450 | X5: ='Age by income band distribution'!L8+'Age by income band distribution'!M8 -> 11210 | Y5: ='Age by income band distribution'!N8+'Age by income band distribution'!O8+'Age by income band distribution'!P8 -> 6330
A6: 3000 | B6: ='Income tables 2001-24'!K12 -> 60660 | C6: ='Income tables 2001-24'!AP12 -> 46360 | D6: ='Income tables 2001-24'!BR12 -> 37290 | E6: ='Income tables 2001-24'!BU12 -> 38310 | F6: ='Income tables 2001-24'!L12 -> 150.9 | G6: ='Income tables 2001-24'!AQ12 -> 115.7 | H6: ='Income tables 2001-24'!BS12 -> 92.73 | I6: ='Income tables 2001-24'!BV12 -> 95 | J6: ='Income tables 2001-24'!M12 -> 21.2 | K6: ='Income tables 2001-24'!AR12 -> 12.1 | L6: ='Income tables 2001-24'!BT12 -> 9.7348547 | M6: ='Income tables 2001-24'!BW12 -> 9.9725451 | Q6: $1,001 - $2,000 | R6: ='Age by income band distribution'!B9 -> 40 | S6: ='Age by income band distribution'!C9 -> 8000 | T6: ='Age by income band distribution'!D9+'Age by income band distribution'!E9 -> 18360 | U6: ='Age by income band distribution'!F9+'Age by income band distribution'!G9 -> 8100 | V6: ='Age by income band distribution'!H9+'Age by income band distribution'!I9 -> 6380 | W6: ='Age by income band distribution'!J9+'Age by income band distribution'!K9 -> 4390 | X6: ='Age by income band distribution'!L9+'Age by income band distribution'!M9 -> 5050 | Y6: ='Age by income band distribution'!N9+'Age by income band distribution'!O9+'Age by income band distribution'!P9 -> 3410
A7: 4000 | B7: ='Income tables 2001-24'!K13 -> 55380 | C7: ='Income tables 2001-24'!AP13 -> 42390 | D7: ='Income tables 2001-24'!BR13 -> 31960 | E7: ='Income tables 2001-24'!BU13 -> 33200 | F7: ='Income tables 2001-24'!L13 -> 193.9 | G7: ='Income tables 2001-24'!AQ13 -> 148.4 | H7: ='Income tables 2001-24'!BS13 -> 111.58 | I7: ='Income tables 2001-24'!BV13 -> 115.89 | J7: ='Income tables 2001-24'!M13 -> 27.5 | K7: ='Income tables 2001-24'!AR13 -> 15.6 | L7: ='Income tables 2001-24'!BT13 -> 11.714206 | M7: ='Income tables 2001-24'!BW13 -> 12.165652 | Q7: $2,001 - $3,000 | R7: ='Age by income band distribution'!B10 -> 30 | S7: ='Age by income band distribution'!C10 -> 2620 | T7: ='Age by income band distribution'!D10+'Age by income band distribution'!E10 -> 14810 | U7: ='Age by income band distribution'!F10+'Age by income band distribution'!G10 -> 6340 | V7: ='Age by income band distribution'!H10+'Age by income band distribution'!I10 -> 4740 | W7: ='Age by income band distribution'!J10+'Age by income band distribution'!K10 -> 3220 | X7: ='Age by income band distribution'!L10+'Age by income band distribution'!M10 -> 3880 | Y7: ='Age by income band distribution'!N10+'Age by income band distribution'!O10+'Age by income band distribution'!P10 -> 2680
A8: 5000 | B8: ='Income tables 2001-24'!K14 -> 52620 | C8: ='Income tables 2001-24'!AP14 -> 39930 | D8: ='Income tables 2001-24'!BR14 -> 30670 | E8: ='Income tables 2001-24'!BU14 -> 30890 | F8: ='Income tables 2001-24'!L14 -> 236.6 | G8: ='Income tables 2001-24'!AQ14 -> 179.9 | H8: ='Income tables 2001-24'!BS14 -> 137.96 | I8: ='Income tables 2001-24'!BV14 -> 138.84 | J8: ='Income tables 2001-24'!M14 -> 34.2 | K8: ='Income tables 2001-24'!AR14 -> 18.9 | L8: ='Income tables 2001-24'!BT14 -> 14.484135 | M8: ='Income tables 2001-24'!BW14 -> 14.575737 | Q8: $3,001 - $4,000 | R8: ='Age by income band distribution'!B11 -> 20 | S8: ='Age by income band distribution'!C11 -> 1360 | T8: ='Age by income band distribution'!D11+'Age by income band distribution'!E11 -> 13420 | U8: ='Age by income band distribution'!F11+'Age by income band distribution'!G11 -> 5760 | V8: ='Age by income band distribution'!H11+'Age by income band distribution'!I11 -> 3980 | W8: ='Age by income band distribution'!J11+'Age by income band distribution'!K11 -> 2840 | X8: ='Age by income band distribution'!L11+'Age by income band distribution'!M11 -> 3370 | Y8: ='Age by income band distribution'!N11+'Age by income band distribution'!O11+'Age by income band distribution'!P11 -> 2460
A9: 6000 | B9: ='Income tables 2001-24'!K15 -> 50480 | C9: ='Income tables 2001-24'!AP15 -> 42470 | D9: ='Income tables 2001-24'!BR15 -> 29310 | E9: ='Income tables 2001-24'!BU15 -> 29510 | F9: ='Income tables 2001-24'!L15 -> 277.4 | G9: ='Income tables 2001-24'!AQ15 -> 233.7 | H9: ='Income tables 2001-24'!BS15 -> 161.08 | I9: ='Income tables 2001-24'!BV15 -> 162.21 | J9: ='Income tables 2001-24'!M15 -> 40.2 | K9: ='Income tables 2001-24'!AR15 -> 24.5 | L9: ='Income tables 2001-24'!BT15 -> 16.910683 | M9: ='Income tables 2001-24'!BW15 -> 17.029922 | Q9: $4,001 - $5,000 | R9: ='Age by income band distribution'!B12 -> 10 | S9: ='Age by income band distribution'!C12 -> 920 | T9: ='Age by income band distribution'!D12+'Age by income band distribution'!E12 -> 12740 | U9: ='Age by income band distribution'!F12+'Age by income band distribution'!G12 -> 5410 | V9: ='Age by income band distribution'!H12+'Age by income band distribution'!I12 -> 3780 | W9: ='Age by income band distribution'!J12+'Age by income band distribution'!K12 -> 2510 | X9: ='Age by income band distribution'!L12+'Age by income band distribution'!M12 -> 3100 | Y9: ='Age by income band distribution'!N12+'Age by income band distribution'!O12+'Age by income band distribution'!P12 -> 2410
A10: 7000 | B10: ='Income tables 2001-24'!K16 -> 48990 | C10: ='Income tables 2001-24'!AP16 -> 42340 | D10: ='Income tables 2001-24'!BR16 -> 28580 | E10: ='Income tables 2001-24'!BU16 -> 28180 | F10: ='Income tables 2001-24'!L16 -> 318.4 | G10: ='Income tables 2001-24'!AQ16 -> 275.4 | H10: ='Income tables 2001-24'!BS16 -> 185.82 | I10: ='Income tables 2001-24'!BV16 -> 183.06 | J10: ='Income tables 2001-24'!M16 -> 46.7 | K10: ='Income tables 2001-24'!AR16 -> 28.9 | L10: ='Income tables 2001-24'!BT16 -> 19.50658 | M10: ='Income tables 2001-24'!BW16 -> 19.219654 | Q10: $5,001 - $6,000 | R10: ='Age by income band distribution'!B13 -> 20 | S10: ='Age by income band distribution'!C13 -> 660 | T10: ='Age by income band distribution'!D13+'Age by income band distribution'!E13 -> 12390 | U10: ='Age by income band distribution'!F13+'Age by income band distribution'!G13 -> 5250 | V10: ='Age by income band distribution'!H13+'Age by income band distribution'!I13 -> 3580 | W10: ='Age by income band distribution'!J13+'Age by income band distribution'!K13 -> 2380 | X10: ='Age by income band distribution'!L13+'Age by income band distribution'!M13 -> 2940 | Y10: ='Age by income band distribution'!N13+'Age by income band distribution'!O13+'Age by income band distribution'!P13 -> 2290
A11: 8000 | B11: ='Income tables 2001-24'!K17 -> 49790 | C11: ='Income tables 2001-24'!AP17 -> 42630 | D11: ='Income tables 2001-24'!BR17 -> 27550 | E11: ='Income tables 2001-24'!BU17 -> 27930 | F11: ='Income tables 2001-24'!L17 -> 373.3 | G11: ='Income tables 2001-24'!AQ17 -> 319.6 | H11: ='Income tables 2001-24'!BS17 -> 206.76 | I11: ='Income tables 2001-24'!BV17 -> 209.48 | J11: ='Income tables 2001-24'!M17 -> 55.7 | K11: ='Income tables 2001-24'!AR17 -> 33.5 | L11: ='Income tables 2001-24'!BT17 -> 21.706567 | M11: ='Income tables 2001-24'!BW17 -> 21.992846 | Q11: $6,001 - $7,000 | R11: ='Age by income band distribution'!B14 -> 20 | S11: ='Age by income band distribution'!C14 -> 540 | T11: ='Age by income band distribution'!D14+'Age by income band distribution'!E14 -> 11990 | U11: ='Age by income band distribution'!F14+'Age by income band distribution'!G14 -> 5000 | V11: ='Age by income band distribution'!H14+'Age by income band distribution'!I14 -> 3310 | W11: ='Age by income band distribution'!J14+'Age by income band distribution'!K14 -> 2240 | X11: ='Age by income band distribution'!L14+'Age by income band distribution'!M14 -> 2780 | Y11: ='Age by income band distribution'!N14+'Age by income band distribution'!O14+'Age by income band distribution'!P14 -> 2320
A12: 9000 | B12: ='Income tables 2001-24'!K18 -> 75090 | C12: ='Income tables 2001-24'!AP18 -> 42460 | D12: ='Income tables 2001-24'!BR18 -> 27480 | E12: ='Income tables 2001-24'!BU18 -> 27310 | F12: ='Income tables 2001-24'!L18 -> 638.6 | G12: ='Income tables 2001-24'!AQ18 -> 361.3 | H12: ='Income tables 2001-24'!BS18 -> 233.68 | I12: ='Income tables 2001-24'!BV18 -> 232.06 | J12: ='Income tables 2001-24'!M18 -> 95.7 | K12: ='Income tables 2001-24'!AR18 -> 37.9 | L12: ='Income tables 2001-24'!BT18 -> 24.533875 | M12: ='Income tables 2001-24'!BW18 -> 24.365142 | Q12: $7,001 - $8,000 | R12: ='Age by income band distribution'!B15 -> 10 | S12: ='Age by income band distribution'!C15 -> 540 | T12: ='Age by income band distribution'!D15+'Age by income band distribution'!E15 -> 11580 | U12: ='Age by income band distribution'!F15+'Age by income band distribution'!G15 -> 5150 | V12: ='Age by income band distribution'!H15+'Age by income band distribution'!I15 -> 3400 | W12: ='Age by income band distribution'!J15+'Age by income band distribution'!K15 -> 2290 | X12: ='Age by income band distribution'!L15+'Age by income band distribution'!M15 -> 2710 | Y12: ='Age by income band distribution'!N15+'Age by income band distribution'!O15+'Age by income band distribution'!P15 -> 2230
A13: 10000 | B13: ='Income tables 2001-24'!K19 -> 62970 | C13: ='Income tables 2001-24'!AP19 -> 54710 | D13: ='Income tables 2001-24'!BR19 -> 27540 | E13: ='Income tables 2001-24'!BU19 -> 27190 | F13: ='Income tables 2001-24'!L19 -> 603.2 | G13: ='Income tables 2001-24'!AQ19 -> 525.9 | H13: ='Income tables 2001-24'!BS19 -> 261.83 | I13: ='Income tables 2001-24'!BV19 -> 258.38 | J13: ='Income tables 2001-24'!M19 -> 91.6 | K13: ='Income tables 2001-24'!AR19 -> 55.2 | L13: ='Income tables 2001-24'!BT19 -> 27.490687 | M13: ='Income tables 2001-24'!BW19 -> 27.125485 | Q13: $8,001 - $9,000 | R13: ='Age by income band distribution'!B16 -> 10 | S13: ='Age by income band distribution'!C16 -> 350 | T13: ='Age by income band distribution'!D16+'Age by income band distribution'!E16 -> 11210 | U13: ='Age by income band distribution'!F16+'Age by income band distribution'!G16 -> 5080 | V13: ='Age by income band distribution'!H16+'Age by income band distribution'!I16 -> 3350 | W13: ='Age by income band distribution'!J16+'Age by income band distribution'!K16 -> 2360 | X13: ='Age by income band distribution'!L16+'Age by income band distribution'!M16 -> 2720 | Y13: ='Age by income band distribution'!N16+'Age by income band distribution'!O16+'Age by income band distribution'!P16 -> 2240
A14: 11000 | B14: ='Income tables 2001-24'!K20 -> 88570 | C14: ='Income tables 2001-24'!AP20 -> 41450 | D14: ='Income tables 2001-24'!BR20 -> 27850 | E14: ='Income tables 2001-24'!BU20 -> 27490 | F14: ='Income tables 2001-24'!L20 -> 922.6 | G14: ='Income tables 2001-24'!AQ20 -> 435.3 | H14: ='Income tables 2001-24'!BS20 -> 292.46 | I14: ='Income tables 2001-24'!BV20 -> 288.69 | J14: ='Income tables 2001-24'!M20 -> 143.8 | K14: ='Income tables 2001-24'!AR20 -> 45.7 | L14: ='Income tables 2001-24'!BT20 -> 30.704438 | M14: ='Income tables 2001-24'!BW20 -> 30.306395 | Q14: $9,001 - $10,000 | R14: ='Age by income band distribution'!B17 -> 20 | S14: ='Age by income band distribution'!C17 -> 320 | T14: ='Age by income band distribution'!D17+'Age by income band distribution'!E17 -> 11200 | U14: ='Age by income band distribution'!F17+'Age by income band distribution'!G17 -> 4880 | V14: ='Age by income band distribution'!H17+'Age by income band distribution'!I17 -> 3310 | W14: ='Age by income band distribution'!J17+'Age by income band distribution'!K17 -> 2270 | X14: ='Age by income band distribution'!L17+'Age by income band distribution'!M17 -> 2840 | Y14: ='Age by income band distribution'!N17+'Age by income band distribution'!O17+'Age by income band distribution'!P17 -> 2380
A15: 12000 | B15: ='Income tables 2001-24'!K21 -> 188070 | C15: ='Income tables 2001-24'!AP21 -> 69820 | D15: ='Income tables 2001-24'!BR21 -> 27380 | E15: ='Income tables 2001-24'!BU21 -> 27530 | F15: ='Income tables 2001-24'!L21 -> 2178.8 | G15: ='Income tables 2001-24'!AQ21 -> 815.3 | H15: ='Income tables 2001-24'!BS21 -> 314.9 | I15: ='Income tables 2001-24'!BV21 -> 316.75 | J15: ='Income tables 2001-24'!M21 -> 351 | K15: ='Income tables 2001-24'!AR21 -> 85.5 | L15: ='Income tables 2001-24'!BT21 -> 33.060519 | M15: ='Income tables 2001-24'!BW21 -> 33.253305 | Q15: $10,001 - $11,000 | R15: ='Age by income band distribution'!B18 -> 20 | S15: ='Age by income band distribution'!C18 -> 280 | T15: ='Age by income band distribution'!D18+'Age by income band distribution'!E18 -> 11220 | U15: ='Age by income band distribution'!F18+'Age by income band distribution'!G18 -> 4960 | V15: ='Age by income band distribution'!H18+'Age by income band distribution'!I18 -> 3400 | W15: ='Age by income band distribution'!J18+'Age by income band distribution'!K18 -> 2440 | X15: ='Age by income band distribution'!L18+'Age by income band distribution'!M18 -> 2740 | Y15: ='Age by income band distribution'!N18+'Age by income band distribution'!O18+'Age by income band distribution'!P18 -> 2430
... A153: 150000 | B153: ='Income tables 2001-24'!K159 -> 210 | C153: ='Income tables 2001-24'!AP159 -> 1750 | D153: ='Income tables 2001-24'!BR159 -> 3980 | E153: ='Income tables 2001-24'!BU159 -> 4920 | F153: ='Income tables 2001-24'!L159 -> 31.4 | G153: ='Income tables 2001-24'!AQ159 -> 261.8 | H153: ='Income tables 2001-24'!BS159 -> 594.99 | I153: ='Income tables 2001-24'!BV159 -> 735.2 | J153: ='Income tables 2001-24'!M159 -> 10.4 | K153: ='Income tables 2001-24'!AR159 -> 70.5 | L153: ='Income tables 2001-24'!BT159 -> 160.2159 | M153: ='Income tables 2001-24'!BW159 -> 197.97037 | Q153: $148,001 - $149,000 | R153: ='Age by income band distribution'!B156 -> 10 | S153: ='Age by income band distribution'!C156 -> 0 | T153: ='Age by income band distribution'!D156+'Age by income band distribution'!E156 -> 20 | U153: ='Age by income band distribution'!F156+'Age by income band distribution'!G156 -> 640 | V153: ='Age by income band distribution'!H156+'Age by income band distribution'!I156 -> 1280 | W153: ='Age by income band distribution'!J156+'Age by income band distribution'!K156 -> 1180 | X153: ='Age by income band distribution'!L156+'Age by income band distribution'!M156 -> 880 | Y153: ='Age by income band distribution'!N156+'Age by income band distribution'!O156+'Age by income band distribution'!P156 -> 540
A154: 151000 | C154: ='Income tables 2001-24'!AP160 -> 1280 | D154: ='Income tables 2001-24'!BR160 -> 4330 | E154: ='Income tables 2001-24'!BU160 -> 5240 | G154: ='Income tables 2001-24'!AQ160 -> 192.6 | H154: ='Income tables 2001-24'!BS160 -> 651.26 | I154: ='Income tables 2001-24'!BV160 -> 788.69 | K154: ='Income tables 2001-24'!AR160 -> 51.9 | L154: ='Income tables 2001-24'!BT160 -> 175.60983 | M154: ='Income tables 2001-24'!BW160 -> 212.66936 | Q154: $149,001 - $150,000 | R154: ='Age by income band distribution'!B157 -> 0 | S154: ='Age by income band distribution'!C157 -> 0 | T154: ='Age by income band distribution'!D157+'Age by income band distribution'!E157 -> 20 | U154: ='Age by income band distribution'!F157+'Age by income band distribution'!G157 -> 720 | V154: ='Age by income band distribution'!H157+'Age by income band distribution'!I157 -> 1360 | W154: ='Age by income band distribution'!J157+'Age by income band distribution'!K157 -> 1320 | X154: ='Age by income band distribution'!L157+'Age by income band distribution'!M157 -> 990 | Y154: ='Age by income band distribution'!N157+'Age by income band distribution'!O157+'Age by income band distribution'!P157 -> 510
A155: 152000 | C155: ='Income tables 2001-24'!AP161 -> 1080 | D155: ='Income tables 2001-24'!BR161 -> 3520 | E155: ='Income tables 2001-24'!BU161 -> 4540 | G155: ='Income tables 2001-24'!AQ161 -> 163.5 | H155: ='Income tables 2001-24'!BS161 -> 533.11 | I155: ='Income tables 2001-24'!BV161 -> 687.8 | K155: ='Income tables 2001-24'!AR161 -> 44.2 | L155: ='Income tables 2001-24'!BT161 -> 143.97383 | M155: ='Income tables 2001-24'!BW161 -> 185.74909 | Q155: $150,001 - $151,000 | R155: ='Age by income band distribution'!B158 -> 10 | S155: ='Age by income band distribution'!C158 -> 0 | T155: ='Age by income band distribution'!D158+'Age by income band distribution'!E158 -> 20 | U155: ='Age by income band distribution'!F158+'Age by income band distribution'!G158 -> 650 | V155: ='Age by income band distribution'!H158+'Age by income band distribution'!I158 -> 1530 | W155: ='Age by income band distribution'!J158+'Age by income band distribution'!K158 -> 1430 | X155: ='Age by income band distribution'!L158+'Age by income band distribution'!M158 -> 1080 | Y155: ='Age by income band distribution'!N158+'Age by income band distribution'!O158+'Age by income band distribution'!P158 -> 540
A156: 153000 | C156: ='Income tables 2001-24'!AP162 -> 1380 | D156: ='Income tables 2001-24'!BR162 -> 3490 | E156: ='Income tables 2001-24'!BU162 -> 4400 | G156: ='Income tables 2001-24'!AQ162 -> 210.5 | H156: ='Income tables 2001-24'!BS162 -> 531.49 | I156: ='Income tables 2001-24'!BV162 -> 671.6 | K156: ='Income tables 2001-24'!AR162 -> 56.9 | L156: ='Income tables 2001-24'!BT162 -> 143.74917 | M156: ='Income tables 2001-24'!BW162 -> 181.63899 | Q156: $151,001 - $152,000 | R156: ='Age by income band distribution'!B159 -> 10 | S156: ='Age by income band distribution'!C159 -> 0 | T156: ='Age by income band distribution'!D159+'Age by income band distribution'!E159 -> 10 | U156: ='Age by income band distribution'!F159+'Age by income band distribution'!G159 -> 610 | V156: ='Age by income band distribution'!H159+'Age by income band distribution'!I159 -> 1310 | W156: ='Age by income band distribution'!J159+'Age by income band distribution'!K159 -> 1120 | X156: ='Age by income band distribution'!L159+'Age by income band distribution'!M159 -> 980 | Y156: ='Age by income band distribution'!N159+'Age by income band distribution'!O159+'Age by income band distribution'!P159 -> 500
A157: 154000 | C157: ='Income tables 2001-24'!AP163 -> 1290 | D157: ='Income tables 2001-24'!BR163 -> 3360 | E157: ='Income tables 2001-24'!BU163 -> 4270 | G157: ='Income tables 2001-24'!AQ163 -> 198 | H157: ='Income tables 2001-24'!BS163 -> 515.75 | I157: ='Income tables 2001-24'!BV163 -> 655.44 | K157: ='Income tables 2001-24'!AR163 -> 53.6 | L157: ='Income tables 2001-24'!BT163 -> 139.68707 | M157: ='Income tables 2001-24'!BW163 -> 177.5251 | Q157: $152,001 - $153,000 | R157: ='Age by income band distribution'!B160 -> 10 | S157: ='Age by income band distribution'!C160 -> 0 | T157: ='Age by income band distribution'!D160+'Age by income band distribution'!E160 -> 20 | U157: ='Age by income band distribution'!F160+'Age by income band distribution'!G160 -> 580 | V157: ='Age by income band distribution'!H160+'Age by income band distribution'!I160 -> 1240 | W157: ='Age by income band distribution'!J160+'Age by income band distribution'!K160 -> 1170 | X157: ='Age by income band distribution'!L160+'Age by income band distribution'!M160 -> 920 | Y157: ='Age by income band distribution'!N160+'Age by income band distribution'!O160+'Age by income band distribution'!P160 -> 480
A158: 155000 | C158: ='Income tables 2001-24'!AP164 -> 860 | D158: ='Income tables 2001-24'!BR164 -> 3420 | E158: ='Income tables 2001-24'!BU164 -> 4100 | G158: ='Income tables 2001-24'!AQ164 -> 132.9 | H158: ='Income tables 2001-24'!BS164 -> 528.23 | I158: ='Income tables 2001-24'!BV164 -> 634.07 | K158: ='Income tables 2001-24'!AR164 -> 36 | L158: ='Income tables 2001-24'!BT164 -> 143.27133 | M158: ='Income tables 2001-24'!BW164 -> 171.97887 | Q158: $153,001 - $154,000 | R158: ='Age by income band distribution'!B161 -> 10 | S158: ='Age by income band distribution'!C161 -> 0 | T158: ='Age by income band distribution'!D161+'Age by income band distribution'!E161 -> 20 | U158: ='Age by income band distribution'!F161+'Age by income band distribution'!G161 -> 570 | V158: ='Age by income band distribution'!H161+'Age by income band distribution'!I161 -> 1150 | W158: ='Age by income band distribution'!J161+'Age by income band distribution'!K161 -> 1110 | X158: ='Age by income band distribution'!L161+'Age by income band distribution'!M161 -> 940 | Y158: ='Age by income band distribution'!N161+'Age by income band distribution'!O161+'Age by income band distribution'!P161 -> 470
A159: 156000 | C159: ='Income tables 2001-24'!AP165 -> 1060 | D159: ='Income tables 2001-24'!BR165 -> 3380 | E159: ='Income tables 2001-24'!BU165 -> 4230 | G159: ='Income tables 2001-24'!AQ165 -> 164.9 | H159: ='Income tables 2001-24'!BS165 -> 525.4 | I159: ='Income tables 2001-24'!BV165 -> 658.35 | K159: ='Income tables 2001-24'!AR165 -> 44.8 | L159: ='Income tables 2001-24'!BT165 -> 142.70027 | M159: ='Income tables 2001-24'!BW165 -> 178.81088 | Q159: $154,001 - $155,000 | R159: ='Age by income band distribution'!B162 -> 0 | S159: ='Age by income band distribution'!C162 -> 0 | T159: ='Age by income band distribution'!D162+'Age by income band distribution'!E162 -> 10 | U159: ='Age by income band distribution'!F162+'Age by income band distribution'!G162 -> 530 | V159: ='Age by income band distribution'!H162+'Age by income band distribution'!I162 -> 1150 | W159: ='Age by income band distribution'!J162+'Age by income band distribution'!K162 -> 1090 | X159: ='Age by income band distribution'!L162+'Age by income band distribution'!M162 -> 830 | Y159: ='Age by income band distribution'!N162+'Age by income band distribution'!O162+'Age by income band distribution'!P162 -> 480
A160: 157000 | C160: ='Income tables 2001-24'!AP166 -> 820 | D160: ='Income tables 2001-24'!BR166 -> 3180 | E160: ='Income tables 2001-24'!BU166 -> 3930 | G160: ='Income tables 2001-24'!AQ166 -> 128.3 | H160: ='Income tables 2001-24'!BS166 -> 497.47 | I160: ='Income tables 2001-24'!BV166 -> 614.25 | K160: ='Income tables 2001-24'!AR166 -> 34.9 | L160: ='Income tables 2001-24'!BT166 -> 135.29886 | M160: ='Income tables 2001-24'!BW166 -> 167.06417 | Q160: $155,001 - $156,000 | R160: ='Age by income band distribution'!B163 -> 0 | S160: ='Age by income band distribution'!C163 -> 0 | T160: ='Age by income band distribution'!D163+'Age by income band distribution'!E163 -> 10 | U160: ='Age by income band distribution'!F163+'Age by income band distribution'!G163 -> 520 | V160: ='Age by income band distribution'!H163+'Age by income band distribution'!I163 -> 1200 | W160: ='Age by income band distribution'!J163+'Age by income band distribution'!K163 -> 1140 | X160: ='Age by income band distribution'!L163+'Age by income band distribution'!M163 -> 870 | Y160: ='Age by income band distribution'!N163+'Age by income band distribution'!O163+'Age by income band distribution'!P163 -> 500
A161: 158000 | C161: ='Income tables 2001-24'!AP167 -> 1010 | D161: ='Income tables 2001-24'!BR167 -> 3070 | E161: ='Income tables 2001-24'!BU167 -> 3920 | G161: ='Income tables 2001-24'!AQ167 -> 159.1 | H161: ='Income tables 2001-24'!BS167 -> 483.35 | I161: ='Income tables 2001-24'!BV167 -> 617.08 | K161: ='Income tables 2001-24'!AR167 -> 43.3 | L161: ='Income tables 2001-24'!BT167 -> 131.64061 | M161: ='Income tables 2001-24'!BW167 -> 168.06082 | Q161: $156,001 - $157,000 | R161: ='Age by income band distribution'!B164 -> 10 | S161: ='Age by income band distribution'!C164 -> 0 | T161: ='Age by income band distribution'!D164+'Age by income band distribution'!E164 -> 10 | U161: ='Age by income band distribution'!F164+'Age by income band distribution'!G164 -> 530 | V161: ='Age by income band distribution'!H164+'Age by income band distribution'!I164 -> 1090 | W161: ='Age by income band distribution'!J164+'Age by income band distribution'!K164 -> 1050 | X161: ='Age by income band distribution'!L164+'Age by income band distribution'!M164 -> 810 | Y161: ='Age by income band distribution'!N164+'Age by income band distribution'!O164+'Age by income band distribution'!P164 -> 440
A162: 159000 | C162: ='Income tables 2001-24'!AP168 -> 1000 | D162: ='Income tables 2001-24'!BR168 -> 3020 | E162: ='Income tables 2001-24'!BU168 -> 3830 | G162: ='Income tables 2001-24'!AQ168 -> 158.5 | H162: ='Income tables 2001-24'!BS168 -> 478.97 | I162: ='Income tables 2001-24'!BV168 -> 607.37 | K162: ='Income tables 2001-24'!AR168 -> 43.2 | L162: ='Income tables 2001-24'!BT168 -> 130.62107 | M162: ='Income tables 2001-24'!BW168 -> 165.6372 | Q162: $157,001 - $158,000 | R162: ='Age by income band distribution'!B165 -> 10 | S162: ='Age by income band distribution'!C165 -> 0 | T162: ='Age by income band distribution'!D165+'Age by income band distribution'!E165 -> 20 | U162: ='Age by income band distribution'!F165+'Age by income band distribution'!G165 -> 460 | V162: ='Age by income band distribution'!H165+'Age by income band distribution'!I165 -> 1090 | W162: ='Age by income band distribution'!J165+'Age by income band distribution'!K165 -> 1060 | X162: ='Age by income band distribution'!L165+'Age by income band distribution'!M165 -> 810 | Y162: ='Age by income band distribution'!N165+'Age by income band distribution'!O165+'Age by income band distribution'!P165 -> 470
A163: 160000 | C163: ='Income tables 2001-24'!AP169 -> 1310 | D163: ='Income tables 2001-24'!BR169 -> 3090 | E163: ='Income tables 2001-24'!BU169 -> 3760 | G163: ='Income tables 2001-24'!AQ169 -> 209 | H163: ='Income tables 2001-24'!BS169 -> 493.23 | I163: ='Income tables 2001-24'!BV169 -> 600.12 | K163: ='Income tables 2001-24'!AR169 -> 57.1 | L163: ='Income tables 2001-24'!BT169 -> 134.6896 | M163: ='Income tables 2001-24'!BW169 -> 163.8805 | Q163: $158,001 - $159,000 | R163: ='Age by income band distribution'!B166 -> 10 | S163: ='Age by income band distribution'!C166 -> 0 | T163: ='Age by income band distribution'!D166+'Age by income band distribution'!E166 -> 10 | U163: ='Age by income band distribution'!F166+'Age by income band distribution'!G166 -> 490 | V163: ='Age by income band distribution'!H166+'Age by income band distribution'!I166 -> 1060 | W163: ='Age by income band distribution'!J166+'Age by income band distribution'!K166 -> 970 | X163: ='Age by income band distribution'!L166+'Age by income band distribution'!M166 -> 850 | Y163: ='Age by income band distribution'!N166+'Age by income band distribution'!O166+'Age by income band distribution'!P166 -> 460
A164: 161000 | C164: ='Income tables 2001-24'!AP170 -> 980 | D164: ='Income tables 2001-24'!BR170 -> 3150 | E164: ='Income tables 2001-24'!BU170 -> 3970 | G164: ='Income tables 2001-24'!AQ170 -> 157.3 | H164: ='Income tables 2001-24'!BS170 -> 505.67 | I164: ='Income tables 2001-24'!BV170 -> 637.27 | K164: ='Income tables 2001-24'!AR170 -> 43 | L164: ='Income tables 2001-24'!BT170 -> 138.26033 | M164: ='Income tables 2001-24'!BW170 -> 174.24281 | Q164: $159,001 - $160,000 | R164: ='Age by income band distribution'!B167 -> 10 | S164: ='Age by income band distribution'!C167 -> 0 | T164: ='Age by income band distribution'!D167+'Age by income band distribution'!E167 -> 10 | U164: ='Age by income band distribution'!F167+'Age by income band distribution'!G167 -> 470 | V164: ='Age by income band distribution'!H167+'Age by income band distribution'!I167 -> 1040 | W164: ='Age by income band distribution'!J167+'Age by income band distribution'!K167 -> 990 | X164: ='Age by income band distribution'!L167+'Age by income band distribution'!M167 -> 830 | Y164: ='Age by income band distribution'!N167+'Age by income band distribution'!O167+'Age by income band distribution'!P167 -> 420
A165: 162000 | C165: ='Income tables 2001-24'!AP171 -> 910 | D165: ='Income tables 2001-24'!BR171 -> 2960 | E165: ='Income tables 2001-24'!BU171 -> 3710 | G165: ='Income tables 2001-24'!AQ171 -> 146.9 | H165: ='Income tables 2001-24'!BS171 -> 478.37 | I165: ='Income tables 2001-24'!BV171 -> 598.37 | K165: ='Income tables 2001-24'!AR171 -> 40.2 | L165: ='Income tables 2001-24'!BT171 -> 130.96639 | M165: ='Income tables 2001-24'!BW171 -> 163.81909 | Q165: $160,001 - $161,000 | R165: ='Age by income band distribution'!B168 -> 0 | S165: ='Age by income band distribution'!C168 -> 0 | T165: ='Age by income band distribution'!D168+'Age by income band distribution'!E168 -> 10 | U165: ='Age by income band distribution'!F168+'Age by income band distribution'!G168 -> 470 | V165: ='Age by income band distribution'!H168+'Age by income band distribution'!I168 -> 1130 | W165: ='Age by income band distribution'!J168+'Age by income band distribution'!K168 -> 1080 | X165: ='Age by income band distribution'!L168+'Age by income band distribution'!M168 -> 850 | Y165: ='Age by income band distribution'!N168+'Age by income band distribution'!O168+'Age by income band distribution'!P168 -> 430
... A186: 183000 | C186: ='Income tables 2001-24'!AP192 -> 670 | D186: ='Income tables 2001-24'!BR192 -> 1980 | E186: ='Income tables 2001-24'!BU192 -> 2510 | G186: ='Income tables 2001-24'!AQ192 -> 122.2 | H186: ='Income tables 2001-24'!BS192 -> 360.61 | I186: ='Income tables 2001-24'!BV192 -> 457.54 | K186: ='Income tables 2001-24'!AR192 -> 34.3 | L186: ='Income tables 2001-24'!BT192 -> 101.35483 | M186: ='Income tables 2001-24'!BW192 -> 128.60225 | Q186: All | R186: ='Age by income band distribution'!B189 -> 5050 | S186: ='Age by income band distribution'!C189 -> 206020 | T186: ='Age by income band distribution'!D189+'Age by income band distribution'!E189 -> 620080 | U186: ='Age by income band distribution'!F189+'Age by income band distribution'!G189 -> 852470 | V186: ='Age by income band distribution'!H189+'Age by income band distribution'!I189 -> 784020 | W186: ='Age by income band distribution'!J189+'Age by income band distribution'!K189 -> 674900 | X186: ='Age by income band distribution'!L189+'Age by income band distribution'!M189 -> 636670 | Y186: ='Age by income band distribution'!N189+'Age by income band distribution'!O189+'Age by income band distribution'!P189 -> 915670
A187: 184000 | C187: ='Income tables 2001-24'!AP193 -> 780 | D187: ='Income tables 2001-24'!BR193 -> 1830 | E187: ='Income tables 2001-24'!BU193 -> 2330 | G187: ='Income tables 2001-24'!AQ193 -> 143.1 | H187: ='Income tables 2001-24'!BS193 -> 335.06 | I187: ='Income tables 2001-24'!BV193 -> 427.18 | K187: ='Income tables 2001-24'!AR193 -> 40.1 | L187: ='Income tables 2001-24'!BT193 -> 94.373033 | M187: ='Income tables 2001-24'!BW193 -> 120.31801
A188: 185000 | C188: ='Income tables 2001-24'!AP194 -> 700 | D188: ='Income tables 2001-24'!BR194 -> 1820 | E188: ='Income tables 2001-24'!BU194 -> 2400 | G188: ='Income tables 2001-24'!AQ194 -> 129.1 | H188: ='Income tables 2001-24'!BS194 -> 335.8 | I188: ='Income tables 2001-24'!BV194 -> 442.26 | K188: ='Income tables 2001-24'!AR194 -> 36.3 | L188: ='Income tables 2001-24'!BT194 -> 94.781616 | M188: ='Income tables 2001-24'!BW194 -> 124.8272
A189: 186000 | C189: ='Income tables 2001-24'!AP195 -> 520 | D189: ='Income tables 2001-24'!BR195 -> 1820 | E189: ='Income tables 2001-24'!BU195 -> 2430 | G189: ='Income tables 2001-24'!AQ195 -> 96.4 | H189: ='Income tables 2001-24'!BS195 -> 338.31 | I189: ='Income tables 2001-24'!BV195 -> 450.16 | K189: ='Income tables 2001-24'!AR195 -> 27.1 | L189: ='Income tables 2001-24'!BT195 -> 95.679923 | M189: ='Income tables 2001-24'!BW195 -> 127.31382
A190: 187000 | C190: ='Income tables 2001-24'!AP196 -> 750 | D190: ='Income tables 2001-24'!BR196 -> 1690 | E190: ='Income tables 2001-24'!BU196 -> 2100 | G190: ='Income tables 2001-24'!AQ196 -> 139.9 | H190: ='Income tables 2001-24'!BS196 -> 314.82 | I190: ='Income tables 2001-24'!BV196 -> 391.24 | K190: ='Income tables 2001-24'!AR196 -> 39.3 | L190: ='Income tables 2001-24'!BT196 -> 89.222864 | M190: ='Income tables 2001-24'!BW196 -> 110.87714
A191: 188000 | C191: ='Income tables 2001-24'!AP197 -> 470 | D191: ='Income tables 2001-24'!BR197 -> 1670 | E191: ='Income tables 2001-24'!BU197 -> 2050 | G191: ='Income tables 2001-24'!AQ197 -> 88.1 | H191: ='Income tables 2001-24'!BS197 -> 313.86 | I191: ='Income tables 2001-24'!BV197 -> 384.79 | K191: ='Income tables 2001-24'!AR197 -> 24.8 | L191: ='Income tables 2001-24'!BT197 -> 89.12533 | M191: ='Income tables 2001-24'!BW197 -> 109.27335
A192: 189000 | C192: ='Income tables 2001-24'!AP198 -> 480 | D192: ='Income tables 2001-24'!BR198 -> 1570 | E192: ='Income tables 2001-24'!BU198 -> 1870 | G192: ='Income tables 2001-24'!AQ198 -> 90.5 | H192: ='Income tables 2001-24'!BS198 -> 296.32 | I192: ='Income tables 2001-24'!BV198 -> 352.3 | K192: ='Income tables 2001-24'!AR198 -> 25.5 | L192: ='Income tables 2001-24'!BT198 -> 84.313082 | M192: ='Income tables 2001-24'!BW198 -> 100.24273
A193: 190000 | C193: ='Income tables 2001-24'!AP199 -> 570 | D193: ='Income tables 2001-24'!BR199 -> 1550 | E193: ='Income tables 2001-24'!BU199 -> 2000 | G193: ='Income tables 2001-24'!AQ199 -> 108 | H193: ='Income tables 2001-24'!BS199 -> 294.31 | I193: ='Income tables 2001-24'!BV199 -> 379 | K193: ='Income tables 2001-24'!AR199 -> 30.5 | L193: ='Income tables 2001-24'!BT199 -> 83.906486 | M193: ='Income tables 2001-24'!BW199 -> 108.05171
A194: 191000 | C194: ='Income tables 2001-24'!AP200 -> 600 | D194: ='Income tables 2001-24'!BR200 -> 1660 | E194: ='Income tables 2001-24'!BU200 -> 2000 | G194: ='Income tables 2001-24'!AQ200 -> 114.3 | H194: ='Income tables 2001-24'!BS200 -> 315.82 | I194: ='Income tables 2001-24'!BV200 -> 381.74 | K194: ='Income tables 2001-24'!AR200 -> 32.3 | L194: ='Income tables 2001-24'!BT200 -> 90.209701 | M194: ='Income tables 2001-24'!BW200 -> 109.03768
A195: 192000 | C195: ='Income tables 2001-24'!AP201 -> 490 | D195: ='Income tables 2001-24'!BR201 -> 1500 | E195: ='Income tables 2001-24'!BU201 -> 1890 | G195: ='Income tables 2001-24'!AQ201 -> 93.8 | H195: ='Income tables 2001-24'!BS201 -> 286.49 | I195: ='Income tables 2001-24'!BV201 -> 362.11 | K195: ='Income tables 2001-24'!AR201 -> 26.5 | L195: ='Income tables 2001-24'!BT201 -> 81.991552 | M195: ='Income tables 2001-24'!BW201 -> 103.63146
A196: 193000 | C196: ='Income tables 2001-24'!AP202 -> 710 | D196: ='Income tables 2001-24'!BR202 -> 1460 | E196: ='Income tables 2001-24'!BU202 -> 1800 | G196: ='Income tables 2001-24'!AQ202 -> 136.7 | H196: ='Income tables 2001-24'!BS202 -> 281.61 | I196: ='Income tables 2001-24'!BV202 -> 345.52 | K196: ='Income tables 2001-24'!AR202 -> 38.7 | L196: ='Income tables 2001-24'!BT202 -> 80.744842 | M196: ='Income tables 2001-24'!BW202 -> 99.067389
A197: 194000 | C197: ='Income tables 2001-24'!AP203 -> 380 | D197: ='Income tables 2001-24'!BR203 -> 1370 | E197: ='Income tables 2001-24'!BU203 -> 1750 | G197: ='Income tables 2001-24'!AQ203 -> 73.6 | H197: ='Income tables 2001-24'!BS203 -> 265.1 | I197: ='Income tables 2001-24'!BV203 -> 338.42 | K197: ='Income tables 2001-24'!AR203 -> 20.8 | L197: ='Income tables 2001-24'!BT203 -> 76.152906 | M197: ='Income tables 2001-24'!BW203 -> 97.215267
A198: 195000 | C198: ='Income tables 2001-24'!AP204 -> 570 | D198: ='Income tables 2001-24'!BR204 -> 1420 | E198: ='Income tables 2001-24'!BU204 -> 1740 | G198: ='Income tables 2001-24'!AQ204 -> 110.9 | H198: ='Income tables 2001-24'!BS204 -> 275.41 | I198: ='Income tables 2001-24'!BV204 -> 337.65 | K198: ='Income tables 2001-24'!AR204 -> 31.4 | L198: ='Income tables 2001-24'!BT204 -> 79.26021 | M198: ='Income tables 2001-24'!BW204 -> 97.171652
... A203: 200000 | C203: ='Income tables 2001-24'!AP209 -> 680 | D203: ='Income tables 2001-24'!BR209 -> 1350 | E203: ='Income tables 2001-24'!BU209 -> 1740 | G203: ='Income tables 2001-24'!AQ209 -> 135.7 | H203: ='Income tables 2001-24'!BS209 -> 268.8 | I203: ='Income tables 2001-24'!BV209 -> 347.38 | K203: ='Income tables 2001-24'!AR209 -> 38.6 | L203: ='Income tables 2001-24'!BT209 -> 78.053788 | M203: ='Income tables 2001-24'!BW209 -> 100.8659
